{
  "date": "2025-09-23",
  "source_file": "lhb_overview_20250101_20260211.csv",
  "summary": {
    "total_count": 74,
    "up_count": 50,
    "down_count": 24,
    "flat_count": 0,
    "avg_change": 5.4306,
    "market_counts": {
      "HS": 32,
      "KCB": 6,
      "SZ": 34,
      "BJ": 2
    }
  },
  "market_breakdown": [
    {
      "code": "BJ",
      "label": "京市",
      "count": 2
    },
    {
      "code": "HS",
      "label": "沪市",
      "count": 32
    },
    {
      "code": "KCB",
      "label": "科创板",
      "count": 6
    },
    {
      "code": "SZ",
      "label": "深市",
      "count": 34
    }
  ],
  "top_gainers": [
    {
      "trade_date": "2025-09-23",
      "security_code": "603418",
      "security_name": "友升股份",
      "market_group": "HS",
      "market_label": "沪市",
      "change_rate": 71.484,
      "trade_market_code": "069001001001",
      "security_type_code": "058001001",
      "detail_link": "https://data.eastmoney.com/stock/lhb,2025-09-23,603418.html",
      "quote_link": "https://quote.eastmoney.com/unify/r/1.603418"
    },
    {
      "trade_date": "2025-09-23",
      "security_code": "688373",
      "security_name": "盟科药业",
      "market_group": "KCB",
      "market_label": "科创板",
      "change_rate": 20.0247,
      "trade_market_code": "069001001006",
      "security_type_code": "058001001",
      "detail_link": "https://data.eastmoney.com/stock/lhb,2025-09-23,688373.html",
      "quote_link": "https://quote.eastmoney.com/unify/r/1.688373"
    },
    {
      "trade_date": "2025-09-23",
      "security_code": "300604",
      "security_name": "长川科技",
      "market_group": "SZ",
      "market_label": "深市",
      "change_rate": 20.003,
      "trade_market_code": "069001002002",
      "security_type_code": "058001001",
      "detail_link": "https://data.eastmoney.com/stock/lhb,2025-09-23,300604.html",
      "quote_link": "https://quote.eastmoney.com/unify/r/0.300604"
    },
    {
      "trade_date": "2025-09-23",
      "security_code": "300111",
      "security_name": "向日葵",
      "market_group": "SZ",
      "market_label": "深市",
      "change_rate": 20.0,
      "trade_market_code": "069001002002",
      "security_type_code": "058001001",
      "detail_link": "https://data.eastmoney.com/stock/lhb,2025-09-23,300111.html",
      "quote_link": "https://quote.eastmoney.com/unify/r/0.300111"
    },
    {
      "trade_date": "2025-09-23",
      "security_code": "301421",
      "security_name": "波长光电",
      "market_group": "SZ",
      "market_label": "深市",
      "change_rate": 20.0,
      "trade_market_code": "069001002002",
      "security_type_code": "058001001",
      "detail_link": "https://data.eastmoney.com/stock/lhb,2025-09-23,301421.html",
      "quote_link": "https://quote.eastmoney.com/unify/r/0.301421"
    },
    {
      "trade_date": "2025-09-23",
      "security_code": "301629",
      "security_name": "矽电股份",
      "market_group": "SZ",
      "market_label": "深市",
      "change_rate": 19.9989,
      "trade_market_code": "069001002002",
      "security_type_code": "058001001",
      "detail_link": "https://data.eastmoney.com/stock/lhb,2025-09-23,301629.html",
      "quote_link": "https://quote.eastmoney.com/unify/r/0.301629"
    },
    {
      "trade_date": "2025-09-23",
      "security_code": "300250",
      "security_name": "初灵信息",
      "market_group": "SZ",
      "market_label": "深市",
      "change_rate": 19.9909,
      "trade_market_code": "069001002002",
      "security_type_code": "058001001",
      "detail_link": "https://data.eastmoney.com/stock/lhb,2025-09-23,300250.html",
      "quote_link": "https://quote.eastmoney.com/unify/r/0.300250"
    },
    {
      "trade_date": "2025-09-23",
      "security_code": "688411",
      "security_name": "海博思创",
      "market_group": "KCB",
      "market_label": "科创板",
      "change_rate": 18.5873,
      "trade_market_code": "069001001006",
      "security_type_code": "058001001",
      "detail_link": "https://data.eastmoney.com/stock/lhb,2025-09-23,688411.html",
      "quote_link": "https://quote.eastmoney.com/unify/r/1.688411"
    },
    {
      "trade_date": "2025-09-23",
      "security_code": "688627",
      "security_name": "精智达",
      "market_group": "KCB",
      "market_label": "科创板",
      "change_rate": 16.9739,
      "trade_market_code": "069001001006",
      "security_type_code": "058001001",
      "detail_link": "https://data.eastmoney.com/stock/lhb,2025-09-23,688627.html",
      "quote_link": "https://quote.eastmoney.com/unify/r/1.688627"
    },
    {
      "trade_date": "2025-09-23",
      "security_code": "688206",
      "security_name": "概伦电子",
      "market_group": "KCB",
      "market_label": "科创板",
      "change_rate": 16.7917,
      "trade_market_code": "069001001006",
      "security_type_code": "058001001",
      "detail_link": "https://data.eastmoney.com/stock/lhb,2025-09-23,688206.html",
      "quote_link": "https://quote.eastmoney.com/unify/r/1.688206"
    }
  ],
  "top_losers": [
    {
      "trade_date": "2025-09-23",
      "security_code": "300366",
      "security_name": "ST创意",
      "market_group": "SZ",
      "market_label": "深市",
      "change_rate": -19.9746,
      "trade_market_code": "069001002005",
      "security_type_code": "058001001",
      "detail_link": "https://data.eastmoney.com/stock/lhb,2025-09-23,300366.html",
      "quote_link": "https://quote.eastmoney.com/unify/r/0.300366"
    },
    {
      "trade_date": "2025-09-23",
      "security_code": "000428",
      "security_name": "华天酒店",
      "market_group": "SZ",
      "market_label": "深市",
      "change_rate": -10.1036,
      "trade_market_code": "069001002001",
      "security_type_code": "058001001",
      "detail_link": "https://data.eastmoney.com/stock/lhb,2025-09-23,000428.html",
      "quote_link": "https://quote.eastmoney.com/unify/r/0.000428"
    },
    {
      "trade_date": "2025-09-23",
      "security_code": "600658",
      "security_name": "电子城",
      "market_group": "HS",
      "market_label": "沪市",
      "change_rate": -10.0152,
      "trade_market_code": "069001001001",
      "security_type_code": "058001001",
      "detail_link": "https://data.eastmoney.com/stock/lhb,2025-09-23,600658.html",
      "quote_link": "https://quote.eastmoney.com/unify/r/1.600658"
    },
    {
      "trade_date": "2025-09-23",
      "security_code": "002059",
      "security_name": "云南旅游",
      "market_group": "SZ",
      "market_label": "深市",
      "change_rate": -10.0124,
      "trade_market_code": "069001002001",
      "security_type_code": "058001001",
      "detail_link": "https://data.eastmoney.com/stock/lhb,2025-09-23,002059.html",
      "quote_link": "https://quote.eastmoney.com/unify/r/0.002059"
    },
    {
      "trade_date": "2025-09-23",
      "security_code": "600749",
      "security_name": "西藏旅游",
      "market_group": "HS",
      "market_label": "沪市",
      "change_rate": -10.009,
      "trade_market_code": "069001001001",
      "security_type_code": "058001001",
      "detail_link": "https://data.eastmoney.com/stock/lhb,2025-09-23,600749.html",
      "quote_link": "https://quote.eastmoney.com/unify/r/1.600749"
    },
    {
      "trade_date": "2025-09-23",
      "security_code": "603189",
      "security_name": "网达软件",
      "market_group": "HS",
      "market_label": "沪市",
      "change_rate": -10.0085,
      "trade_market_code": "069001001001",
      "security_type_code": "058001001",
      "detail_link": "https://data.eastmoney.com/stock/lhb,2025-09-23,603189.html",
      "quote_link": "https://quote.eastmoney.com/unify/r/1.603189"
    },
    {
      "trade_date": "2025-09-23",
      "security_code": "603280",
      "security_name": "南方路机",
      "market_group": "HS",
      "market_label": "沪市",
      "change_rate": -10.0074,
      "trade_market_code": "069001001001",
      "security_type_code": "058001001",
      "detail_link": "https://data.eastmoney.com/stock/lhb,2025-09-23,603280.html",
      "quote_link": "https://quote.eastmoney.com/unify/r/1.603280"
    },
    {
      "trade_date": "2025-09-23",
      "security_code": "603848",
      "security_name": "好太太",
      "market_group": "HS",
      "market_label": "沪市",
      "change_rate": -10.0074,
      "trade_market_code": "069001001001",
      "security_type_code": "058001001",
      "detail_link": "https://data.eastmoney.com/stock/lhb,2025-09-23,603848.html",
      "quote_link": "https://quote.eastmoney.com/unify/r/1.603848"
    },
    {
      "trade_date": "2025-09-23",
      "security_code": "002905",
      "security_name": "金逸影视",
      "market_group": "SZ",
      "market_label": "深市",
      "change_rate": -9.992,
      "trade_market_code": "069001002001",
      "security_type_code": "058001001",
      "detail_link": "https://data.eastmoney.com/stock/lhb,2025-09-23,002905.html",
      "quote_link": "https://quote.eastmoney.com/unify/r/0.002905"
    },
    {
      "trade_date": "2025-09-23",
      "security_code": "601929",
      "security_name": "吉视传媒",
      "market_group": "HS",
      "market_label": "沪市",
      "change_rate": -9.7674,
      "trade_market_code": "069001001001",
      "security_type_code": "058001001",
      "detail_link": "https://data.eastmoney.com/stock/lhb,2025-09-23,601929.html",
      "quote_link": "https://quote.eastmoney.com/unify/r/1.601929"
    }
  ],
  "stocks": [
    {
      "trade_date": "2025-09-23",
      "security_code": "600103",
      "security_name": "青山纸业",
      "market_group": "HS",
      "market_label": "沪市",
      "change_rate": -9.4148,
      "trade_market_code": "069001001001",
      "security_type_code": "058001001",
      "detail_link": "https://data.eastmoney.com/stock/lhb,2025-09-23,600103.html",
      "quote_link": "https://quote.eastmoney.com/unify/r/1.600103"
    },
    {
      "trade_date": "2025-09-23",
      "security_code": "600105",
      "security_name": "永鼎股份",
      "market_group": "HS",
      "market_label": "沪市",
      "change_rate": 10.0,
      "trade_market_code": "069001001001",
      "security_type_code": "058001001",
      "detail_link": "https://data.eastmoney.com/stock/lhb,2025-09-23,600105.html",
      "quote_link": "https://quote.eastmoney.com/unify/r/1.600105"
    },
    {
      "trade_date": "2025-09-23",
      "security_code": "600170",
      "security_name": "上海建工",
      "market_group": "HS",
      "market_label": "沪市",
      "change_rate": 7.6923,
      "trade_market_code": "069001001001",
      "security_type_code": "058001001",
      "detail_link": "https://data.eastmoney.com/stock/lhb,2025-09-23,600170.html",
      "quote_link": "https://quote.eastmoney.com/unify/r/1.600170"
    },
    {
      "trade_date": "2025-09-23",
      "security_code": "600322",
      "security_name": "津投城开",
      "market_group": "HS",
      "market_label": "沪市",
      "change_rate": -7.6364,
      "trade_market_code": "069001001001",
      "security_type_code": "058001001",
      "detail_link": "https://data.eastmoney.com/stock/lhb,2025-09-23,600322.html",
      "quote_link": "https://quote.eastmoney.com/unify/r/1.600322"
    },
    {
      "trade_date": "2025-09-23",
      "security_code": "600376",
      "security_name": "首开股份",
      "market_group": "HS",
      "market_label": "沪市",
      "change_rate": -4.1302,
      "trade_market_code": "069001001001",
      "security_type_code": "058001001",
      "detail_link": "https://data.eastmoney.com/stock/lhb,2025-09-23,600376.html",
      "quote_link": "https://quote.eastmoney.com/unify/r/1.600376"
    },
    {
      "trade_date": "2025-09-23",
      "security_code": "600400",
      "security_name": "红豆股份",
      "market_group": "HS",
      "market_label": "沪市",
      "change_rate": -4.918,
      "trade_market_code": "069001001001",
      "security_type_code": "058001001",
      "detail_link": "https://data.eastmoney.com/stock/lhb,2025-09-23,600400.html",
      "quote_link": "https://quote.eastmoney.com/unify/r/1.600400"
    },
    {
      "trade_date": "2025-09-23",
      "security_code": "600619",
      "security_name": "海立股份",
      "market_group": "HS",
      "market_label": "沪市",
      "change_rate": 6.3223,
      "trade_market_code": "069001001001",
      "security_type_code": "058001001",
      "detail_link": "https://data.eastmoney.com/stock/lhb,2025-09-23,600619.html",
      "quote_link": "https://quote.eastmoney.com/unify/r/1.600619"
    },
    {
      "trade_date": "2025-09-23",
      "security_code": "600635",
      "security_name": "大众公用",
      "market_group": "HS",
      "market_label": "沪市",
      "change_rate": 9.9819,
      "trade_market_code": "069001001001",
      "security_type_code": "058001001",
      "detail_link": "https://data.eastmoney.com/stock/lhb,2025-09-23,600635.html",
      "quote_link": "https://quote.eastmoney.com/unify/r/1.600635"
    },
    {
      "trade_date": "2025-09-23",
      "security_code": "600658",
      "security_name": "电子城",
      "market_group": "HS",
      "market_label": "沪市",
      "change_rate": -10.0152,
      "trade_market_code": "069001001001",
      "security_type_code": "058001001",
      "detail_link": "https://data.eastmoney.com/stock/lhb,2025-09-23,600658.html",
      "quote_link": "https://quote.eastmoney.com/unify/r/1.600658"
    },
    {
      "trade_date": "2025-09-23",
      "security_code": "600735",
      "security_name": "ST新华锦",
      "market_group": "HS",
      "market_label": "沪市",
      "change_rate": 10.0707,
      "trade_market_code": "069001001003",
      "security_type_code": "058001001",
      "detail_link": "https://data.eastmoney.com/stock/lhb,2025-09-23,600735.html",
      "quote_link": "https://quote.eastmoney.com/unify/r/1.600735"
    },
    {
      "trade_date": "2025-09-23",
      "security_code": "600749",
      "security_name": "西藏旅游",
      "market_group": "HS",
      "market_label": "沪市",
      "change_rate": -10.009,
      "trade_market_code": "069001001001",
      "security_type_code": "058001001",
      "detail_link": "https://data.eastmoney.com/stock/lhb,2025-09-23,600749.html",
      "quote_link": "https://quote.eastmoney.com/unify/r/1.600749"
    },
    {
      "trade_date": "2025-09-23",
      "security_code": "600797",
      "security_name": "浙大网新",
      "market_group": "HS",
      "market_label": "沪市",
      "change_rate": 4.1415,
      "trade_market_code": "069001001001",
      "security_type_code": "058001001",
      "detail_link": "https://data.eastmoney.com/stock/lhb,2025-09-23,600797.html",
      "quote_link": "https://quote.eastmoney.com/unify/r/1.600797"
    },
    {
      "trade_date": "2025-09-23",
      "security_code": "600895",
      "security_name": "张江高科",
      "market_group": "HS",
      "market_label": "沪市",
      "change_rate": 10.0095,
      "trade_market_code": "069001001001",
      "security_type_code": "058001001",
      "detail_link": "https://data.eastmoney.com/stock/lhb,2025-09-23,600895.html",
      "quote_link": "https://quote.eastmoney.com/unify/r/1.600895"
    },
    {
      "trade_date": "2025-09-23",
      "security_code": "601022",
      "security_name": "宁波远洋",
      "market_group": "HS",
      "market_label": "沪市",
      "change_rate": 7.722,
      "trade_market_code": "069001001001",
      "security_type_code": "058001001",
      "detail_link": "https://data.eastmoney.com/stock/lhb,2025-09-23,601022.html",
      "quote_link": "https://quote.eastmoney.com/unify/r/1.601022"
    },
    {
      "trade_date": "2025-09-23",
      "security_code": "601929",
      "security_name": "吉视传媒",
      "market_group": "HS",
      "market_label": "沪市",
      "change_rate": -9.7674,
      "trade_market_code": "069001001001",
      "security_type_code": "058001001",
      "detail_link": "https://data.eastmoney.com/stock/lhb,2025-09-23,601929.html",
      "quote_link": "https://quote.eastmoney.com/unify/r/1.601929"
    },
    {
      "trade_date": "2025-09-23",
      "security_code": "603007",
      "security_name": "*ST花王",
      "market_group": "HS",
      "market_label": "沪市",
      "change_rate": 3.0361,
      "trade_market_code": "069001001003",
      "security_type_code": "058001001",
      "detail_link": "https://data.eastmoney.com/stock/lhb,2025-09-23,603007.html",
      "quote_link": "https://quote.eastmoney.com/unify/r/1.603007"
    },
    {
      "trade_date": "2025-09-23",
      "security_code": "603035",
      "security_name": "常熟汽饰",
      "market_group": "HS",
      "market_label": "沪市",
      "change_rate": 10.0312,
      "trade_market_code": "069001001001",
      "security_type_code": "058001001",
      "detail_link": "https://data.eastmoney.com/stock/lhb,2025-09-23,603035.html",
      "quote_link": "https://quote.eastmoney.com/unify/r/1.603035"
    },
    {
      "trade_date": "2025-09-23",
      "security_code": "603166",
      "security_name": "福达股份",
      "market_group": "HS",
      "market_label": "沪市",
      "change_rate": 10.0264,
      "trade_market_code": "069001001001",
      "security_type_code": "058001001",
      "detail_link": "https://data.eastmoney.com/stock/lhb,2025-09-23,603166.html",
      "quote_link": "https://quote.eastmoney.com/unify/r/1.603166"
    },
    {
      "trade_date": "2025-09-23",
      "security_code": "603189",
      "security_name": "网达软件",
      "market_group": "HS",
      "market_label": "沪市",
      "change_rate": -10.0085,
      "trade_market_code": "069001001001",
      "security_type_code": "058001001",
      "detail_link": "https://data.eastmoney.com/stock/lhb,2025-09-23,603189.html",
      "quote_link": "https://quote.eastmoney.com/unify/r/1.603189"
    },
    {
      "trade_date": "2025-09-23",
      "security_code": "603239",
      "security_name": "浙江仙通",
      "market_group": "HS",
      "market_label": "沪市",
      "change_rate": 9.9852,
      "trade_market_code": "069001001001",
      "security_type_code": "058001001",
      "detail_link": "https://data.eastmoney.com/stock/lhb,2025-09-23,603239.html",
      "quote_link": "https://quote.eastmoney.com/unify/r/1.603239"
    },
    {
      "trade_date": "2025-09-23",
      "security_code": "603280",
      "security_name": "南方路机",
      "market_group": "HS",
      "market_label": "沪市",
      "change_rate": -10.0074,
      "trade_market_code": "069001001001",
      "security_type_code": "058001001",
      "detail_link": "https://data.eastmoney.com/stock/lhb,2025-09-23,603280.html",
      "quote_link": "https://quote.eastmoney.com/unify/r/1.603280"
    },
    {
      "trade_date": "2025-09-23",
      "security_code": "603322",
      "security_name": "超讯通信",
      "market_group": "HS",
      "market_label": "沪市",
      "change_rate": 10.0108,
      "trade_market_code": "069001001001",
      "security_type_code": "058001001",
      "detail_link": "https://data.eastmoney.com/stock/lhb,2025-09-23,603322.html",
      "quote_link": "https://quote.eastmoney.com/unify/r/1.603322"
    },
    {
      "trade_date": "2025-09-23",
      "security_code": "603370",
      "security_name": "华新精科",
      "market_group": "HS",
      "market_label": "沪市",
      "change_rate": 2.3112,
      "trade_market_code": "069001001001",
      "security_type_code": "058001001",
      "detail_link": "https://data.eastmoney.com/stock/lhb,2025-09-23,603370.html",
      "quote_link": "https://quote.eastmoney.com/unify/r/1.603370"
    },
    {
      "trade_date": "2025-09-23",
      "security_code": "603418",
      "security_name": "友升股份",
      "market_group": "HS",
      "market_label": "沪市",
      "change_rate": 71.484,
      "trade_market_code": "069001001001",
      "security_type_code": "058001001",
      "detail_link": "https://data.eastmoney.com/stock/lhb,2025-09-23,603418.html",
      "quote_link": "https://quote.eastmoney.com/unify/r/1.603418"
    },
    {
      "trade_date": "2025-09-23",
      "security_code": "603421",
      "security_name": "鼎信通讯",
      "market_group": "HS",
      "market_label": "沪市",
      "change_rate": -0.3672,
      "trade_market_code": "069001001001",
      "security_type_code": "058001001",
      "detail_link": "https://data.eastmoney.com/stock/lhb,2025-09-23,603421.html",
      "quote_link": "https://quote.eastmoney.com/unify/r/1.603421"
    },
    {
      "trade_date": "2025-09-23",
      "security_code": "603618",
      "security_name": "杭电股份",
      "market_group": "HS",
      "market_label": "沪市",
      "change_rate": 9.982,
      "trade_market_code": "069001001001",
      "security_type_code": "058001001",
      "detail_link": "https://data.eastmoney.com/stock/lhb,2025-09-23,603618.html",
      "quote_link": "https://quote.eastmoney.com/unify/r/1.603618"
    },
    {
      "trade_date": "2025-09-23",
      "security_code": "603686",
      "security_name": "福龙马",
      "market_group": "HS",
      "market_label": "沪市",
      "change_rate": 9.9882,
      "trade_market_code": "069001001001",
      "security_type_code": "058001001",
      "detail_link": "https://data.eastmoney.com/stock/lhb,2025-09-23,603686.html",
      "quote_link": "https://quote.eastmoney.com/unify/r/1.603686"
    },
    {
      "trade_date": "2025-09-23",
      "security_code": "603848",
      "security_name": "好太太",
      "market_group": "HS",
      "market_label": "沪市",
      "change_rate": -10.0074,
      "trade_market_code": "069001001001",
      "security_type_code": "058001001",
      "detail_link": "https://data.eastmoney.com/stock/lhb,2025-09-23,603848.html",
      "quote_link": "https://quote.eastmoney.com/unify/r/1.603848"
    },
    {
      "trade_date": "2025-09-23",
      "security_code": "603903",
      "security_name": "中持股份",
      "market_group": "HS",
      "market_label": "沪市",
      "change_rate": 10.0375,
      "trade_market_code": "069001001001",
      "security_type_code": "058001001",
      "detail_link": "https://data.eastmoney.com/stock/lhb,2025-09-23,603903.html",
      "quote_link": "https://quote.eastmoney.com/unify/r/1.603903"
    },
    {
      "trade_date": "2025-09-23",
      "security_code": "605055",
      "security_name": "迎丰股份",
      "market_group": "HS",
      "market_label": "沪市",
      "change_rate": 10.023,
      "trade_market_code": "069001001001",
      "security_type_code": "058001001",
      "detail_link": "https://data.eastmoney.com/stock/lhb,2025-09-23,605055.html",
      "quote_link": "https://quote.eastmoney.com/unify/r/1.605055"
    },
    {
      "trade_date": "2025-09-23",
      "security_code": "605255",
      "security_name": "天普股份",
      "market_group": "HS",
      "market_label": "沪市",
      "change_rate": 10.004,
      "trade_market_code": "069001001001",
      "security_type_code": "058001001",
      "detail_link": "https://data.eastmoney.com/stock/lhb,2025-09-23,605255.html",
      "quote_link": "https://quote.eastmoney.com/unify/r/1.605255"
    },
    {
      "trade_date": "2025-09-23",
      "security_code": "900939",
      "security_name": "汇丽B",
      "market_group": "HS",
      "market_label": "沪市",
      "change_rate": 6.5839,
      "trade_market_code": "069001001001",
      "security_type_code": "058001002",
      "detail_link": "https://data.eastmoney.com/stock/lhb,2025-09-23,900939.html",
      "quote_link": "https://quote.eastmoney.com/unify/r/1.900939"
    },
    {
      "trade_date": "2025-09-23",
      "security_code": "688206",
      "security_name": "概伦电子",
      "market_group": "KCB",
      "market_label": "科创板",
      "change_rate": 16.7917,
      "trade_market_code": "069001001006",
      "security_type_code": "058001001",
      "detail_link": "https://data.eastmoney.com/stock/lhb,2025-09-23,688206.html",
      "quote_link": "https://quote.eastmoney.com/unify/r/1.688206"
    },
    {
      "trade_date": "2025-09-23",
      "security_code": "688332",
      "security_name": "中科蓝讯",
      "market_group": "KCB",
      "market_label": "科创板",
      "change_rate": 7.996,
      "trade_market_code": "069001001006",
      "security_type_code": "058001001",
      "detail_link": "https://data.eastmoney.com/stock/lhb,2025-09-23,688332.html",
      "quote_link": "https://quote.eastmoney.com/unify/r/1.688332"
    },
    {
      "trade_date": "2025-09-23",
      "security_code": "688373",
      "security_name": "盟科药业",
      "market_group": "KCB",
      "market_label": "科创板",
      "change_rate": 20.0247,
      "trade_market_code": "069001001006",
      "security_type_code": "058001001",
      "detail_link": "https://data.eastmoney.com/stock/lhb,2025-09-23,688373.html",
      "quote_link": "https://quote.eastmoney.com/unify/r/1.688373"
    },
    {
      "trade_date": "2025-09-23",
      "security_code": "688411",
      "security_name": "海博思创",
      "market_group": "KCB",
      "market_label": "科创板",
      "change_rate": 18.5873,
      "trade_market_code": "069001001006",
      "security_type_code": "058001001",
      "detail_link": "https://data.eastmoney.com/stock/lhb,2025-09-23,688411.html",
      "quote_link": "https://quote.eastmoney.com/unify/r/1.688411"
    },
    {
      "trade_date": "2025-09-23",
      "security_code": "688627",
      "security_name": "精智达",
      "market_group": "KCB",
      "market_label": "科创板",
      "change_rate": 16.9739,
      "trade_market_code": "069001001006",
      "security_type_code": "058001001",
      "detail_link": "https://data.eastmoney.com/stock/lhb,2025-09-23,688627.html",
      "quote_link": "https://quote.eastmoney.com/unify/r/1.688627"
    },
    {
      "trade_date": "2025-09-23",
      "security_code": "688660",
      "security_name": "电气风电",
      "market_group": "KCB",
      "market_label": "科创板",
      "change_rate": 15.5458,
      "trade_market_code": "069001001006",
      "security_type_code": "058001001",
      "detail_link": "https://data.eastmoney.com/stock/lhb,2025-09-23,688660.html",
      "quote_link": "https://quote.eastmoney.com/unify/r/1.688660"
    },
    {
      "trade_date": "2025-09-23",
      "security_code": "000014",
      "security_name": "沙河股份",
      "market_group": "SZ",
      "market_label": "深市",
      "change_rate": 10.0261,
      "trade_market_code": "069001002001",
      "security_type_code": "058001001",
      "detail_link": "https://data.eastmoney.com/stock/lhb,2025-09-23,000014.html",
      "quote_link": "https://quote.eastmoney.com/unify/r/0.000014"
    },
    {
      "trade_date": "2025-09-23",
      "security_code": "000428",
      "security_name": "华天酒店",
      "market_group": "SZ",
      "market_label": "深市",
      "change_rate": -10.1036,
      "trade_market_code": "069001002001",
      "security_type_code": "058001001",
      "detail_link": "https://data.eastmoney.com/stock/lhb,2025-09-23,000428.html",
      "quote_link": "https://quote.eastmoney.com/unify/r/0.000428"
    },
    {
      "trade_date": "2025-09-23",
      "security_code": "000559",
      "security_name": "万向钱潮",
      "market_group": "SZ",
      "market_label": "深市",
      "change_rate": 9.98,
      "trade_market_code": "069001002001",
      "security_type_code": "058001001",
      "detail_link": "https://data.eastmoney.com/stock/lhb,2025-09-23,000559.html",
      "quote_link": "https://quote.eastmoney.com/unify/r/0.000559"
    },
    {
      "trade_date": "2025-09-23",
      "security_code": "000718",
      "security_name": "苏宁环球",
      "market_group": "SZ",
      "market_label": "深市",
      "change_rate": -3.6765,
      "trade_market_code": "069001002001",
      "security_type_code": "058001001",
      "detail_link": "https://data.eastmoney.com/stock/lhb,2025-09-23,000718.html",
      "quote_link": "https://quote.eastmoney.com/unify/r/0.000718"
    },
    {
      "trade_date": "2025-09-23",
      "security_code": "000721",
      "security_name": "西安饮食",
      "market_group": "SZ",
      "market_label": "深市",
      "change_rate": -8.7805,
      "trade_market_code": "069001002001",
      "security_type_code": "058001001",
      "detail_link": "https://data.eastmoney.com/stock/lhb,2025-09-23,000721.html",
      "quote_link": "https://quote.eastmoney.com/unify/r/0.000721"
    },
    {
      "trade_date": "2025-09-23",
      "security_code": "000981",
      "security_name": "山子高科",
      "market_group": "SZ",
      "market_label": "深市",
      "change_rate": -0.4695,
      "trade_market_code": "069001002001",
      "security_type_code": "058001001",
      "detail_link": "https://data.eastmoney.com/stock/lhb,2025-09-23,000981.html",
      "quote_link": "https://quote.eastmoney.com/unify/r/0.000981"
    },
    {
      "trade_date": "2025-09-23",
      "security_code": "001221",
      "security_name": "悍高集团",
      "market_group": "SZ",
      "market_label": "深市",
      "change_rate": -5.296,
      "trade_market_code": "069001002001",
      "security_type_code": "058001001",
      "detail_link": "https://data.eastmoney.com/stock/lhb,2025-09-23,001221.html",
      "quote_link": "https://quote.eastmoney.com/unify/r/0.001221"
    },
    {
      "trade_date": "2025-09-23",
      "security_code": "001234",
      "security_name": "泰慕士",
      "market_group": "SZ",
      "market_label": "深市",
      "change_rate": 9.9889,
      "trade_market_code": "069001002001",
      "security_type_code": "058001001",
      "detail_link": "https://data.eastmoney.com/stock/lhb,2025-09-23,001234.html",
      "quote_link": "https://quote.eastmoney.com/unify/r/0.001234"
    },
    {
      "trade_date": "2025-09-23",
      "security_code": "001309",
      "security_name": "德明利",
      "market_group": "SZ",
      "market_label": "深市",
      "change_rate": 9.9994,
      "trade_market_code": "069001002001",
      "security_type_code": "058001001",
      "detail_link": "https://data.eastmoney.com/stock/lhb,2025-09-23,001309.html",
      "quote_link": "https://quote.eastmoney.com/unify/r/0.001309"
    },
    {
      "trade_date": "2025-09-23",
      "security_code": "002059",
      "security_name": "云南旅游",
      "market_group": "SZ",
      "market_label": "深市",
      "change_rate": -10.0124,
      "trade_market_code": "069001002001",
      "security_type_code": "058001001",
      "detail_link": "https://data.eastmoney.com/stock/lhb,2025-09-23,002059.html",
      "quote_link": "https://quote.eastmoney.com/unify/r/0.002059"
    },
    {
      "trade_date": "2025-09-23",
      "security_code": "002130",
      "security_name": "沃尔核材",
      "market_group": "SZ",
      "market_label": "深市",
      "change_rate": 10.0,
      "trade_market_code": "069001002001",
      "security_type_code": "058001001",
      "detail_link": "https://data.eastmoney.com/stock/lhb,2025-09-23,002130.html",
      "quote_link": "https://quote.eastmoney.com/unify/r/0.002130"
    },
    {
      "trade_date": "2025-09-23",
      "security_code": "002249",
      "security_name": "大洋电机",
      "market_group": "SZ",
      "market_label": "深市",
      "change_rate": 9.9718,
      "trade_market_code": "069001002001",
      "security_type_code": "058001001",
      "detail_link": "https://data.eastmoney.com/stock/lhb,2025-09-23,002249.html",
      "quote_link": "https://quote.eastmoney.com/unify/r/0.002249"
    },
    {
      "trade_date": "2025-09-23",
      "security_code": "002272",
      "security_name": "川润股份",
      "market_group": "SZ",
      "market_label": "深市",
      "change_rate": 5.3059,
      "trade_market_code": "069001002001",
      "security_type_code": "058001001",
      "detail_link": "https://data.eastmoney.com/stock/lhb,2025-09-23,002272.html",
      "quote_link": "https://quote.eastmoney.com/unify/r/0.002272"
    },
    {
      "trade_date": "2025-09-23",
      "security_code": "002298",
      "security_name": "中电鑫龙",
      "market_group": "SZ",
      "market_label": "深市",
      "change_rate": 4.6832,
      "trade_market_code": "069001002001",
      "security_type_code": "058001001",
      "detail_link": "https://data.eastmoney.com/stock/lhb,2025-09-23,002298.html",
      "quote_link": "https://quote.eastmoney.com/unify/r/0.002298"
    },
    {
      "trade_date": "2025-09-23",
      "security_code": "002364",
      "security_name": "中恒电气",
      "market_group": "SZ",
      "market_label": "深市",
      "change_rate": -3.4406,
      "trade_market_code": "069001002001",
      "security_type_code": "058001001",
      "detail_link": "https://data.eastmoney.com/stock/lhb,2025-09-23,002364.html",
      "quote_link": "https://quote.eastmoney.com/unify/r/0.002364"
    },
    {
      "trade_date": "2025-09-23",
      "security_code": "002426",
      "security_name": "胜利精密",
      "market_group": "SZ",
      "market_label": "深市",
      "change_rate": -6.5963,
      "trade_market_code": "069001002001",
      "security_type_code": "058001001",
      "detail_link": "https://data.eastmoney.com/stock/lhb,2025-09-23,002426.html",
      "quote_link": "https://quote.eastmoney.com/unify/r/0.002426"
    },
    {
      "trade_date": "2025-09-23",
      "security_code": "002475",
      "security_name": "立讯精密",
      "market_group": "SZ",
      "market_label": "深市",
      "change_rate": 7.7933,
      "trade_market_code": "069001002001",
      "security_type_code": "058001001",
      "detail_link": "https://data.eastmoney.com/stock/lhb,2025-09-23,002475.html",
      "quote_link": "https://quote.eastmoney.com/unify/r/0.002475"
    },
    {
      "trade_date": "2025-09-23",
      "security_code": "002491",
      "security_name": "通鼎互联",
      "market_group": "SZ",
      "market_label": "深市",
      "change_rate": -9.7521,
      "trade_market_code": "069001002001",
      "security_type_code": "058001001",
      "detail_link": "https://data.eastmoney.com/stock/lhb,2025-09-23,002491.html",
      "quote_link": "https://quote.eastmoney.com/unify/r/0.002491"
    },
    {
      "trade_date": "2025-09-23",
      "security_code": "002513",
      "security_name": "蓝丰生化",
      "market_group": "SZ",
      "market_label": "深市",
      "change_rate": 10.0683,
      "trade_market_code": "069001002001",
      "security_type_code": "058001001",
      "detail_link": "https://data.eastmoney.com/stock/lhb,2025-09-23,002513.html",
      "quote_link": "https://quote.eastmoney.com/unify/r/0.002513"
    },
    {
      "trade_date": "2025-09-23",
      "security_code": "002549",
      "security_name": "凯美特气",
      "market_group": "SZ",
      "market_label": "深市",
      "change_rate": 9.9825,
      "trade_market_code": "069001002001",
      "security_type_code": "058001001",
      "detail_link": "https://data.eastmoney.com/stock/lhb,2025-09-23,002549.html",
      "quote_link": "https://quote.eastmoney.com/unify/r/0.002549"
    },
    {
      "trade_date": "2025-09-23",
      "security_code": "002647",
      "security_name": "*ST仁东",
      "market_group": "SZ",
      "market_label": "深市",
      "change_rate": 4.3417,
      "trade_market_code": "069001002005",
      "security_type_code": "058001001",
      "detail_link": "https://data.eastmoney.com/stock/lhb,2025-09-23,002647.html",
      "quote_link": "https://quote.eastmoney.com/unify/r/0.002647"
    },
    {
      "trade_date": "2025-09-23",
      "security_code": "002674",
      "security_name": "兴业科技",
      "market_group": "SZ",
      "market_label": "深市",
      "change_rate": 10.0322,
      "trade_market_code": "069001002001",
      "security_type_code": "058001001",
      "detail_link": "https://data.eastmoney.com/stock/lhb,2025-09-23,002674.html",
      "quote_link": "https://quote.eastmoney.com/unify/r/0.002674"
    },
    {
      "trade_date": "2025-09-23",
      "security_code": "002905",
      "security_name": "金逸影视",
      "market_group": "SZ",
      "market_label": "深市",
      "change_rate": -9.992,
      "trade_market_code": "069001002001",
      "security_type_code": "058001001",
      "detail_link": "https://data.eastmoney.com/stock/lhb,2025-09-23,002905.html",
      "quote_link": "https://quote.eastmoney.com/unify/r/0.002905"
    },
    {
      "trade_date": "2025-09-23",
      "security_code": "002925",
      "security_name": "盈趣科技",
      "market_group": "SZ",
      "market_label": "深市",
      "change_rate": 10.0204,
      "trade_market_code": "069001002001",
      "security_type_code": "058001001",
      "detail_link": "https://data.eastmoney.com/stock/lhb,2025-09-23,002925.html",
      "quote_link": "https://quote.eastmoney.com/unify/r/0.002925"
    },
    {
      "trade_date": "2025-09-23",
      "security_code": "300111",
      "security_name": "向日葵",
      "market_group": "SZ",
      "market_label": "深市",
      "change_rate": 20.0,
      "trade_market_code": "069001002002",
      "security_type_code": "058001001",
      "detail_link": "https://data.eastmoney.com/stock/lhb,2025-09-23,300111.html",
      "quote_link": "https://quote.eastmoney.com/unify/r/0.300111"
    },
    {
      "trade_date": "2025-09-23",
      "security_code": "300139",
      "security_name": "晓程科技",
      "market_group": "SZ",
      "market_label": "深市",
      "change_rate": 2.0641,
      "trade_market_code": "069001002002",
      "security_type_code": "058001001",
      "detail_link": "https://data.eastmoney.com/stock/lhb,2025-09-23,300139.html",
      "quote_link": "https://quote.eastmoney.com/unify/r/0.300139"
    },
    {
      "trade_date": "2025-09-23",
      "security_code": "300250",
      "security_name": "初灵信息",
      "market_group": "SZ",
      "market_label": "深市",
      "change_rate": 19.9909,
      "trade_market_code": "069001002002",
      "security_type_code": "058001001",
      "detail_link": "https://data.eastmoney.com/stock/lhb,2025-09-23,300250.html",
      "quote_link": "https://quote.eastmoney.com/unify/r/0.300250"
    },
    {
      "trade_date": "2025-09-23",
      "security_code": "300280",
      "security_name": "紫天退",
      "market_group": "SZ",
      "market_label": "深市",
      "change_rate": 2.1739,
      "trade_market_code": "069001002005",
      "security_type_code": "058001001",
      "detail_link": "https://data.eastmoney.com/stock/lhb,2025-09-23,300280.html",
      "quote_link": "https://quote.eastmoney.com/unify/r/0.300280"
    },
    {
      "trade_date": "2025-09-23",
      "security_code": "300366",
      "security_name": "ST创意",
      "market_group": "SZ",
      "market_label": "深市",
      "change_rate": -19.9746,
      "trade_market_code": "069001002005",
      "security_type_code": "058001001",
      "detail_link": "https://data.eastmoney.com/stock/lhb,2025-09-23,300366.html",
      "quote_link": "https://quote.eastmoney.com/unify/r/0.300366"
    },
    {
      "trade_date": "2025-09-23",
      "security_code": "300604",
      "security_name": "长川科技",
      "market_group": "SZ",
      "market_label": "深市",
      "change_rate": 20.003,
      "trade_market_code": "069001002002",
      "security_type_code": "058001001",
      "detail_link": "https://data.eastmoney.com/stock/lhb,2025-09-23,300604.html",
      "quote_link": "https://quote.eastmoney.com/unify/r/0.300604"
    },
    {
      "trade_date": "2025-09-23",
      "security_code": "301013",
      "security_name": "利和兴",
      "market_group": "SZ",
      "market_label": "深市",
      "change_rate": -2.8852,
      "trade_market_code": "069001002002",
      "security_type_code": "058001001",
      "detail_link": "https://data.eastmoney.com/stock/lhb,2025-09-23,301013.html",
      "quote_link": "https://quote.eastmoney.com/unify/r/0.301013"
    },
    {
      "trade_date": "2025-09-23",
      "security_code": "301052",
      "security_name": "果麦文化",
      "market_group": "SZ",
      "market_label": "深市",
      "change_rate": 8.0605,
      "trade_market_code": "069001002002",
      "security_type_code": "058001001",
      "detail_link": "https://data.eastmoney.com/stock/lhb,2025-09-23,301052.html",
      "quote_link": "https://quote.eastmoney.com/unify/r/0.301052"
    },
    {
      "trade_date": "2025-09-23",
      "security_code": "301421",
      "security_name": "波长光电",
      "market_group": "SZ",
      "market_label": "深市",
      "change_rate": 20.0,
      "trade_market_code": "069001002002",
      "security_type_code": "058001001",
      "detail_link": "https://data.eastmoney.com/stock/lhb,2025-09-23,301421.html",
      "quote_link": "https://quote.eastmoney.com/unify/r/0.301421"
    },
    {
      "trade_date": "2025-09-23",
      "security_code": "301629",
      "security_name": "矽电股份",
      "market_group": "SZ",
      "market_label": "深市",
      "change_rate": 19.9989,
      "trade_market_code": "069001002002",
      "security_type_code": "058001001",
      "detail_link": "https://data.eastmoney.com/stock/lhb,2025-09-23,301629.html",
      "quote_link": "https://quote.eastmoney.com/unify/r/0.301629"
    },
    {
      "trade_date": "2025-09-23",
      "security_code": "920022",
      "security_name": "世昌股份",
      "market_group": "BJ",
      "market_label": "京市",
      "change_rate": -3.1105,
      "trade_market_code": "069001017",
      "security_type_code": "058001001",
      "detail_link": "https://data.eastmoney.com/stock/lhb,2025-09-23,920022.html",
      "quote_link": "https://quote.eastmoney.com/unify/r/0.920022"
    },
    {
      "trade_date": "2025-09-23",
      "security_code": "920961",
      "security_name": "创远信科",
      "market_group": "BJ",
      "market_label": "京市",
      "change_rate": 12.3904,
      "trade_market_code": "069001017",
      "security_type_code": "058001001",
      "detail_link": "https://data.eastmoney.com/stock/lhb,2025-09-23,920961.html",
      "quote_link": "https://quote.eastmoney.com/unify/r/0.920961"
    }
  ]
}