{
  "date": "2025-04-28",
  "source_file": "lhb_overview_20250101_20260211.csv",
  "summary": {
    "total_count": 84,
    "up_count": 39,
    "down_count": 44,
    "flat_count": 1,
    "avg_change": -1.3229,
    "market_counts": {
      "HS": 28,
      "KCB": 2,
      "SZ": 47,
      "BJ": 6,
      "KZZ": 1
    }
  },
  "market_breakdown": [
    {
      "code": "BJ",
      "label": "京市",
      "count": 6
    },
    {
      "code": "HS",
      "label": "沪市",
      "count": 28
    },
    {
      "code": "KCB",
      "label": "科创板",
      "count": 2
    },
    {
      "code": "KZZ",
      "label": "可转债",
      "count": 1
    },
    {
      "code": "SZ",
      "label": "深市",
      "count": 47
    }
  ],
  "top_gainers": [
    {
      "trade_date": "2025-04-28",
      "security_code": "301209",
      "security_name": "联合化学",
      "market_group": "SZ",
      "market_label": "深市",
      "change_rate": 20.0,
      "trade_market_code": "069001002002",
      "security_type_code": "058001001",
      "detail_link": "https://data.eastmoney.com/stock/lhb,2025-04-28,301209.html",
      "quote_link": "https://quote.eastmoney.com/unify/r/0.301209"
    },
    {
      "trade_date": "2025-04-28",
      "security_code": "301479",
      "security_name": "弘景光电",
      "market_group": "SZ",
      "market_label": "深市",
      "change_rate": 20.0,
      "trade_market_code": "069001002002",
      "security_type_code": "058001001",
      "detail_link": "https://data.eastmoney.com/stock/lhb,2025-04-28,301479.html",
      "quote_link": "https://quote.eastmoney.com/unify/r/0.301479"
    },
    {
      "trade_date": "2025-04-28",
      "security_code": "301212",
      "security_name": "联盛化学",
      "market_group": "SZ",
      "market_label": "深市",
      "change_rate": 19.9831,
      "trade_market_code": "069001002002",
      "security_type_code": "058001001",
      "detail_link": "https://data.eastmoney.com/stock/lhb,2025-04-28,301212.html",
      "quote_link": "https://quote.eastmoney.com/unify/r/0.301212"
    },
    {
      "trade_date": "2025-04-28",
      "security_code": "300157",
      "security_name": "新锦动力",
      "market_group": "SZ",
      "market_label": "深市",
      "change_rate": 19.9248,
      "trade_market_code": "069001002002",
      "security_type_code": "058001001",
      "detail_link": "https://data.eastmoney.com/stock/lhb,2025-04-28,300157.html",
      "quote_link": "https://quote.eastmoney.com/unify/r/0.300157"
    },
    {
      "trade_date": "2025-04-28",
      "security_code": "688328",
      "security_name": "深科达",
      "market_group": "KCB",
      "market_label": "科创板",
      "change_rate": 15.3236,
      "trade_market_code": "069001001006",
      "security_type_code": "058001001",
      "detail_link": "https://data.eastmoney.com/stock/lhb,2025-04-28,688328.html",
      "quote_link": "https://quote.eastmoney.com/unify/r/1.688328"
    },
    {
      "trade_date": "2025-04-28",
      "security_code": "300945",
      "security_name": "曼卡龙",
      "market_group": "SZ",
      "market_label": "深市",
      "change_rate": 15.102,
      "trade_market_code": "069001002002",
      "security_type_code": "058001001",
      "detail_link": "https://data.eastmoney.com/stock/lhb,2025-04-28,300945.html",
      "quote_link": "https://quote.eastmoney.com/unify/r/0.300945"
    },
    {
      "trade_date": "2025-04-28",
      "security_code": "600828",
      "security_name": "茂业商业",
      "market_group": "HS",
      "market_label": "沪市",
      "change_rate": 10.1149,
      "trade_market_code": "069001001001",
      "security_type_code": "058001001",
      "detail_link": "https://data.eastmoney.com/stock/lhb,2025-04-28,600828.html",
      "quote_link": "https://quote.eastmoney.com/unify/r/1.600828"
    },
    {
      "trade_date": "2025-04-28",
      "security_code": "002354",
      "security_name": "天娱数科",
      "market_group": "SZ",
      "market_label": "深市",
      "change_rate": 10.0671,
      "trade_market_code": "069001002001",
      "security_type_code": "058001001",
      "detail_link": "https://data.eastmoney.com/stock/lhb,2025-04-28,002354.html",
      "quote_link": "https://quote.eastmoney.com/unify/r/0.002354"
    },
    {
      "trade_date": "2025-04-28",
      "security_code": "603065",
      "security_name": "宿迁联盛",
      "market_group": "HS",
      "market_label": "沪市",
      "change_rate": 10.0654,
      "trade_market_code": "069001001001",
      "security_type_code": "058001001",
      "detail_link": "https://data.eastmoney.com/stock/lhb,2025-04-28,603065.html",
      "quote_link": "https://quote.eastmoney.com/unify/r/1.603065"
    },
    {
      "trade_date": "2025-04-28",
      "security_code": "600589",
      "security_name": "大位科技",
      "market_group": "HS",
      "market_label": "沪市",
      "change_rate": 10.0629,
      "trade_market_code": "069001001001",
      "security_type_code": "058001001",
      "detail_link": "https://data.eastmoney.com/stock/lhb,2025-04-28,600589.html",
      "quote_link": "https://quote.eastmoney.com/unify/r/1.600589"
    }
  ],
  "top_losers": [
    {
      "trade_date": "2025-04-28",
      "security_code": "300630",
      "security_name": "普利退",
      "market_group": "SZ",
      "market_label": "深市",
      "change_rate": -73.8956,
      "trade_market_code": "069001002005",
      "security_type_code": "058001001",
      "detail_link": "https://data.eastmoney.com/stock/lhb,2025-04-28,300630.html",
      "quote_link": "https://quote.eastmoney.com/unify/r/0.300630"
    },
    {
      "trade_date": "2025-04-28",
      "security_code": "920305",
      "security_name": "*ST云创",
      "market_group": "BJ",
      "market_label": "京市",
      "change_rate": -29.9817,
      "trade_market_code": "069001017",
      "security_type_code": "058001001",
      "detail_link": "https://data.eastmoney.com/stock/lhb,2025-04-28,920305.html",
      "quote_link": "https://quote.eastmoney.com/unify/r/0.920305"
    },
    {
      "trade_date": "2025-04-28",
      "security_code": "300477",
      "security_name": "ST合纵",
      "market_group": "SZ",
      "market_label": "深市",
      "change_rate": -20.0803,
      "trade_market_code": "069001002005",
      "security_type_code": "058001001",
      "detail_link": "https://data.eastmoney.com/stock/lhb,2025-04-28,300477.html",
      "quote_link": "https://quote.eastmoney.com/unify/r/0.300477"
    },
    {
      "trade_date": "2025-04-28",
      "security_code": "300379",
      "security_name": "东通退",
      "market_group": "SZ",
      "market_label": "深市",
      "change_rate": -20.0308,
      "trade_market_code": "069001002005",
      "security_type_code": "058001001",
      "detail_link": "https://data.eastmoney.com/stock/lhb,2025-04-28,300379.html",
      "quote_link": "https://quote.eastmoney.com/unify/r/0.300379"
    },
    {
      "trade_date": "2025-04-28",
      "security_code": "688788",
      "security_name": "科思科技",
      "market_group": "KCB",
      "market_label": "科创板",
      "change_rate": -20.0,
      "trade_market_code": "069001001006",
      "security_type_code": "058001001",
      "detail_link": "https://data.eastmoney.com/stock/lhb,2025-04-28,688788.html",
      "quote_link": "https://quote.eastmoney.com/unify/r/1.688788"
    },
    {
      "trade_date": "2025-04-28",
      "security_code": "300211",
      "security_name": "*ST亿通",
      "market_group": "SZ",
      "market_label": "深市",
      "change_rate": -19.977,
      "trade_market_code": "069001002005",
      "security_type_code": "058001001",
      "detail_link": "https://data.eastmoney.com/stock/lhb,2025-04-28,300211.html",
      "quote_link": "https://quote.eastmoney.com/unify/r/0.300211"
    },
    {
      "trade_date": "2025-04-28",
      "security_code": "300044",
      "security_name": "ST赛为",
      "market_group": "SZ",
      "market_label": "深市",
      "change_rate": -19.9134,
      "trade_market_code": "069001002005",
      "security_type_code": "058001001",
      "detail_link": "https://data.eastmoney.com/stock/lhb,2025-04-28,300044.html",
      "quote_link": "https://quote.eastmoney.com/unify/r/0.300044"
    },
    {
      "trade_date": "2025-04-28",
      "security_code": "300716",
      "security_name": "ST泉为",
      "market_group": "SZ",
      "market_label": "深市",
      "change_rate": -19.7406,
      "trade_market_code": "069001002005",
      "security_type_code": "058001001",
      "detail_link": "https://data.eastmoney.com/stock/lhb,2025-04-28,300716.html",
      "quote_link": "https://quote.eastmoney.com/unify/r/0.300716"
    },
    {
      "trade_date": "2025-04-28",
      "security_code": "123099",
      "security_name": "普利转退",
      "market_group": "KZZ",
      "market_label": "可转债",
      "change_rate": -18.1327,
      "trade_market_code": "069001002",
      "security_type_code": "060",
      "detail_link": "https://data.eastmoney.com/stock/lhb,2025-04-28,123099.html",
      "quote_link": "https://quote.eastmoney.com/unify/r/0.123099"
    },
    {
      "trade_date": "2025-04-28",
      "security_code": "300205",
      "security_name": "*ST天喻",
      "market_group": "SZ",
      "market_label": "深市",
      "change_rate": -15.4839,
      "trade_market_code": "069001002005",
      "security_type_code": "058001001",
      "detail_link": "https://data.eastmoney.com/stock/lhb,2025-04-28,300205.html",
      "quote_link": "https://quote.eastmoney.com/unify/r/0.300205"
    }
  ],
  "stocks": [
    {
      "trade_date": "2025-04-28",
      "security_code": "600051",
      "security_name": "宁波联合",
      "market_group": "HS",
      "market_label": "沪市",
      "change_rate": -1.7199,
      "trade_market_code": "069001001001",
      "security_type_code": "058001001",
      "detail_link": "https://data.eastmoney.com/stock/lhb,2025-04-28,600051.html",
      "quote_link": "https://quote.eastmoney.com/unify/r/1.600051"
    },
    {
      "trade_date": "2025-04-28",
      "security_code": "600149",
      "security_name": "廊坊发展",
      "market_group": "HS",
      "market_label": "沪市",
      "change_rate": 9.9548,
      "trade_market_code": "069001001001",
      "security_type_code": "058001001",
      "detail_link": "https://data.eastmoney.com/stock/lhb,2025-04-28,600149.html",
      "quote_link": "https://quote.eastmoney.com/unify/r/1.600149"
    },
    {
      "trade_date": "2025-04-28",
      "security_code": "600190",
      "security_name": "退市锦港",
      "market_group": "HS",
      "market_label": "沪市",
      "change_rate": -5.2174,
      "trade_market_code": "069001001003",
      "security_type_code": "058001001",
      "detail_link": "https://data.eastmoney.com/stock/lhb,2025-04-28,600190.html",
      "quote_link": "https://quote.eastmoney.com/unify/r/1.600190"
    },
    {
      "trade_date": "2025-04-28",
      "security_code": "600200",
      "security_name": "退市苏吴",
      "market_group": "HS",
      "market_label": "沪市",
      "change_rate": -9.8734,
      "trade_market_code": "069001001003",
      "security_type_code": "058001001",
      "detail_link": "https://data.eastmoney.com/stock/lhb,2025-04-28,600200.html",
      "quote_link": "https://quote.eastmoney.com/unify/r/1.600200"
    },
    {
      "trade_date": "2025-04-28",
      "security_code": "600381",
      "security_name": "*ST春天",
      "market_group": "HS",
      "market_label": "沪市",
      "change_rate": -4.8387,
      "trade_market_code": "069001001003",
      "security_type_code": "058001001",
      "detail_link": "https://data.eastmoney.com/stock/lhb,2025-04-28,600381.html",
      "quote_link": "https://quote.eastmoney.com/unify/r/1.600381"
    },
    {
      "trade_date": "2025-04-28",
      "security_code": "600396",
      "security_name": "华电辽能",
      "market_group": "HS",
      "market_label": "沪市",
      "change_rate": 9.9668,
      "trade_market_code": "069001001001",
      "security_type_code": "058001001",
      "detail_link": "https://data.eastmoney.com/stock/lhb,2025-04-28,600396.html",
      "quote_link": "https://quote.eastmoney.com/unify/r/1.600396"
    },
    {
      "trade_date": "2025-04-28",
      "security_code": "600505",
      "security_name": "西昌电力",
      "market_group": "HS",
      "market_label": "沪市",
      "change_rate": 0.0,
      "trade_market_code": "069001001001",
      "security_type_code": "058001001",
      "detail_link": "https://data.eastmoney.com/stock/lhb,2025-04-28,600505.html",
      "quote_link": "https://quote.eastmoney.com/unify/r/1.600505"
    },
    {
      "trade_date": "2025-04-28",
      "security_code": "600539",
      "security_name": "狮头股份",
      "market_group": "HS",
      "market_label": "沪市",
      "change_rate": 10.0287,
      "trade_market_code": "069001001001",
      "security_type_code": "058001001",
      "detail_link": "https://data.eastmoney.com/stock/lhb,2025-04-28,600539.html",
      "quote_link": "https://quote.eastmoney.com/unify/r/1.600539"
    },
    {
      "trade_date": "2025-04-28",
      "security_code": "600589",
      "security_name": "大位科技",
      "market_group": "HS",
      "market_label": "沪市",
      "change_rate": 10.0629,
      "trade_market_code": "069001001001",
      "security_type_code": "058001001",
      "detail_link": "https://data.eastmoney.com/stock/lhb,2025-04-28,600589.html",
      "quote_link": "https://quote.eastmoney.com/unify/r/1.600589"
    },
    {
      "trade_date": "2025-04-28",
      "security_code": "600622",
      "security_name": "光大嘉宝",
      "market_group": "HS",
      "market_label": "沪市",
      "change_rate": -10.0324,
      "trade_market_code": "069001001001",
      "security_type_code": "058001001",
      "detail_link": "https://data.eastmoney.com/stock/lhb,2025-04-28,600622.html",
      "quote_link": "https://quote.eastmoney.com/unify/r/1.600622"
    },
    {
      "trade_date": "2025-04-28",
      "security_code": "600726",
      "security_name": "华电能源",
      "market_group": "HS",
      "market_label": "沪市",
      "change_rate": 10.0,
      "trade_market_code": "069001001001",
      "security_type_code": "058001001",
      "detail_link": "https://data.eastmoney.com/stock/lhb,2025-04-28,600726.html",
      "quote_link": "https://quote.eastmoney.com/unify/r/1.600726"
    },
    {
      "trade_date": "2025-04-28",
      "security_code": "600794",
      "security_name": "保税科技",
      "market_group": "HS",
      "market_label": "沪市",
      "change_rate": -10.076,
      "trade_market_code": "069001001001",
      "security_type_code": "058001001",
      "detail_link": "https://data.eastmoney.com/stock/lhb,2025-04-28,600794.html",
      "quote_link": "https://quote.eastmoney.com/unify/r/1.600794"
    },
    {
      "trade_date": "2025-04-28",
      "security_code": "600804",
      "security_name": "退市鹏博",
      "market_group": "HS",
      "market_label": "沪市",
      "change_rate": -4.4118,
      "trade_market_code": "069001001003",
      "security_type_code": "058001001",
      "detail_link": "https://data.eastmoney.com/stock/lhb,2025-04-28,600804.html",
      "quote_link": "https://quote.eastmoney.com/unify/r/1.600804"
    },
    {
      "trade_date": "2025-04-28",
      "security_code": "600822",
      "security_name": "上海物贸",
      "market_group": "HS",
      "market_label": "沪市",
      "change_rate": 9.962,
      "trade_market_code": "069001001001",
      "security_type_code": "058001001",
      "detail_link": "https://data.eastmoney.com/stock/lhb,2025-04-28,600822.html",
      "quote_link": "https://quote.eastmoney.com/unify/r/1.600822"
    },
    {
      "trade_date": "2025-04-28",
      "security_code": "600828",
      "security_name": "茂业商业",
      "market_group": "HS",
      "market_label": "沪市",
      "change_rate": 10.1149,
      "trade_market_code": "069001001001",
      "security_type_code": "058001001",
      "detail_link": "https://data.eastmoney.com/stock/lhb,2025-04-28,600828.html",
      "quote_link": "https://quote.eastmoney.com/unify/r/1.600828"
    },
    {
      "trade_date": "2025-04-28",
      "security_code": "601222",
      "security_name": "林洋能源",
      "market_group": "HS",
      "market_label": "沪市",
      "change_rate": -10.0629,
      "trade_market_code": "069001001001",
      "security_type_code": "058001001",
      "detail_link": "https://data.eastmoney.com/stock/lhb,2025-04-28,601222.html",
      "quote_link": "https://quote.eastmoney.com/unify/r/1.601222"
    },
    {
      "trade_date": "2025-04-28",
      "security_code": "601956",
      "security_name": "东贝集团",
      "market_group": "HS",
      "market_label": "沪市",
      "change_rate": 10.0,
      "trade_market_code": "069001001001",
      "security_type_code": "058001001",
      "detail_link": "https://data.eastmoney.com/stock/lhb,2025-04-28,601956.html",
      "quote_link": "https://quote.eastmoney.com/unify/r/1.601956"
    },
    {
      "trade_date": "2025-04-28",
      "security_code": "603003",
      "security_name": "退市龙宇",
      "market_group": "HS",
      "market_label": "沪市",
      "change_rate": -4.9412,
      "trade_market_code": "069001001003",
      "security_type_code": "058001001",
      "detail_link": "https://data.eastmoney.com/stock/lhb,2025-04-28,603003.html",
      "quote_link": "https://quote.eastmoney.com/unify/r/1.603003"
    },
    {
      "trade_date": "2025-04-28",
      "security_code": "603065",
      "security_name": "宿迁联盛",
      "market_group": "HS",
      "market_label": "沪市",
      "change_rate": 10.0654,
      "trade_market_code": "069001001001",
      "security_type_code": "058001001",
      "detail_link": "https://data.eastmoney.com/stock/lhb,2025-04-28,603065.html",
      "quote_link": "https://quote.eastmoney.com/unify/r/1.603065"
    },
    {
      "trade_date": "2025-04-28",
      "security_code": "603086",
      "security_name": "先达股份",
      "market_group": "HS",
      "market_label": "沪市",
      "change_rate": -2.445,
      "trade_market_code": "069001001001",
      "security_type_code": "058001001",
      "detail_link": "https://data.eastmoney.com/stock/lhb,2025-04-28,603086.html",
      "quote_link": "https://quote.eastmoney.com/unify/r/1.603086"
    },
    {
      "trade_date": "2025-04-28",
      "security_code": "603280",
      "security_name": "南方路机",
      "market_group": "HS",
      "market_label": "沪市",
      "change_rate": 2.9364,
      "trade_market_code": "069001001001",
      "security_type_code": "058001001",
      "detail_link": "https://data.eastmoney.com/stock/lhb,2025-04-28,603280.html",
      "quote_link": "https://quote.eastmoney.com/unify/r/1.603280"
    },
    {
      "trade_date": "2025-04-28",
      "security_code": "603605",
      "security_name": "珀莱雅",
      "market_group": "HS",
      "market_label": "沪市",
      "change_rate": 9.9988,
      "trade_market_code": "069001001001",
      "security_type_code": "058001001",
      "detail_link": "https://data.eastmoney.com/stock/lhb,2025-04-28,603605.html",
      "quote_link": "https://quote.eastmoney.com/unify/r/1.603605"
    },
    {
      "trade_date": "2025-04-28",
      "security_code": "603696",
      "security_name": "安记食品",
      "market_group": "HS",
      "market_label": "沪市",
      "change_rate": 7.9461,
      "trade_market_code": "069001001001",
      "security_type_code": "058001001",
      "detail_link": "https://data.eastmoney.com/stock/lhb,2025-04-28,603696.html",
      "quote_link": "https://quote.eastmoney.com/unify/r/1.603696"
    },
    {
      "trade_date": "2025-04-28",
      "security_code": "603697",
      "security_name": "有友食品",
      "market_group": "HS",
      "market_label": "沪市",
      "change_rate": -10.0,
      "trade_market_code": "069001001001",
      "security_type_code": "058001001",
      "detail_link": "https://data.eastmoney.com/stock/lhb,2025-04-28,603697.html",
      "quote_link": "https://quote.eastmoney.com/unify/r/1.603697"
    },
    {
      "trade_date": "2025-04-28",
      "security_code": "603800",
      "security_name": "洪田股份",
      "market_group": "HS",
      "market_label": "沪市",
      "change_rate": -10.0037,
      "trade_market_code": "069001001001",
      "security_type_code": "058001001",
      "detail_link": "https://data.eastmoney.com/stock/lhb,2025-04-28,603800.html",
      "quote_link": "https://quote.eastmoney.com/unify/r/1.603800"
    },
    {
      "trade_date": "2025-04-28",
      "security_code": "603985",
      "security_name": "恒润股份",
      "market_group": "HS",
      "market_label": "沪市",
      "change_rate": 10.026,
      "trade_market_code": "069001001001",
      "security_type_code": "058001001",
      "detail_link": "https://data.eastmoney.com/stock/lhb,2025-04-28,603985.html",
      "quote_link": "https://quote.eastmoney.com/unify/r/1.603985"
    },
    {
      "trade_date": "2025-04-28",
      "security_code": "900906",
      "security_name": "中毅达B",
      "market_group": "HS",
      "market_label": "沪市",
      "change_rate": 5.0781,
      "trade_market_code": "069001001001",
      "security_type_code": "058001002",
      "detail_link": "https://data.eastmoney.com/stock/lhb,2025-04-28,900906.html",
      "quote_link": "https://quote.eastmoney.com/unify/r/1.900906"
    },
    {
      "trade_date": "2025-04-28",
      "security_code": "900952",
      "security_name": "退市锦B",
      "market_group": "HS",
      "market_label": "沪市",
      "change_rate": -5.5556,
      "trade_market_code": "069001001003",
      "security_type_code": "058001002",
      "detail_link": "https://data.eastmoney.com/stock/lhb,2025-04-28,900952.html",
      "quote_link": "https://quote.eastmoney.com/unify/r/1.900952"
    },
    {
      "trade_date": "2025-04-28",
      "security_code": "688328",
      "security_name": "深科达",
      "market_group": "KCB",
      "market_label": "科创板",
      "change_rate": 15.3236,
      "trade_market_code": "069001001006",
      "security_type_code": "058001001",
      "detail_link": "https://data.eastmoney.com/stock/lhb,2025-04-28,688328.html",
      "quote_link": "https://quote.eastmoney.com/unify/r/1.688328"
    },
    {
      "trade_date": "2025-04-28",
      "security_code": "688788",
      "security_name": "科思科技",
      "market_group": "KCB",
      "market_label": "科创板",
      "change_rate": -20.0,
      "trade_market_code": "069001001006",
      "security_type_code": "058001001",
      "detail_link": "https://data.eastmoney.com/stock/lhb,2025-04-28,688788.html",
      "quote_link": "https://quote.eastmoney.com/unify/r/1.688788"
    },
    {
      "trade_date": "2025-04-28",
      "security_code": "000423",
      "security_name": "东阿阿胶",
      "market_group": "SZ",
      "market_label": "深市",
      "change_rate": -9.9951,
      "trade_market_code": "069001002001",
      "security_type_code": "058001001",
      "detail_link": "https://data.eastmoney.com/stock/lhb,2025-04-28,000423.html",
      "quote_link": "https://quote.eastmoney.com/unify/r/0.000423"
    },
    {
      "trade_date": "2025-04-28",
      "security_code": "000504",
      "security_name": "*ST生物",
      "market_group": "SZ",
      "market_label": "深市",
      "change_rate": -4.0268,
      "trade_market_code": "069001002005",
      "security_type_code": "058001001",
      "detail_link": "https://data.eastmoney.com/stock/lhb,2025-04-28,000504.html",
      "quote_link": "https://quote.eastmoney.com/unify/r/0.000504"
    },
    {
      "trade_date": "2025-04-28",
      "security_code": "000560",
      "security_name": "我爱我家",
      "market_group": "SZ",
      "market_label": "深市",
      "change_rate": -10.0543,
      "trade_market_code": "069001002001",
      "security_type_code": "058001001",
      "detail_link": "https://data.eastmoney.com/stock/lhb,2025-04-28,000560.html",
      "quote_link": "https://quote.eastmoney.com/unify/r/0.000560"
    },
    {
      "trade_date": "2025-04-28",
      "security_code": "000565",
      "security_name": "渝三峡A",
      "market_group": "SZ",
      "market_label": "深市",
      "change_rate": 10.0529,
      "trade_market_code": "069001002001",
      "security_type_code": "058001001",
      "detail_link": "https://data.eastmoney.com/stock/lhb,2025-04-28,000565.html",
      "quote_link": "https://quote.eastmoney.com/unify/r/0.000565"
    },
    {
      "trade_date": "2025-04-28",
      "security_code": "000615",
      "security_name": "*ST美谷",
      "market_group": "SZ",
      "market_label": "深市",
      "change_rate": -5.0595,
      "trade_market_code": "069001002005",
      "security_type_code": "058001001",
      "detail_link": "https://data.eastmoney.com/stock/lhb,2025-04-28,000615.html",
      "quote_link": "https://quote.eastmoney.com/unify/r/0.000615"
    },
    {
      "trade_date": "2025-04-28",
      "security_code": "000622",
      "security_name": "恒立退",
      "market_group": "SZ",
      "market_label": "深市",
      "change_rate": -4.8309,
      "trade_market_code": "069001002005",
      "security_type_code": "058001001",
      "detail_link": "https://data.eastmoney.com/stock/lhb,2025-04-28,000622.html",
      "quote_link": "https://quote.eastmoney.com/unify/r/0.000622"
    },
    {
      "trade_date": "2025-04-28",
      "security_code": "000691",
      "security_name": "*ST亚太",
      "market_group": "SZ",
      "market_label": "深市",
      "change_rate": 10.0346,
      "trade_market_code": "069001002005",
      "security_type_code": "058001001",
      "detail_link": "https://data.eastmoney.com/stock/lhb,2025-04-28,000691.html",
      "quote_link": "https://quote.eastmoney.com/unify/r/0.000691"
    },
    {
      "trade_date": "2025-04-28",
      "security_code": "000736",
      "security_name": "*ST中地",
      "market_group": "SZ",
      "market_label": "深市",
      "change_rate": -5.102,
      "trade_market_code": "069001002005",
      "security_type_code": "058001001",
      "detail_link": "https://data.eastmoney.com/stock/lhb,2025-04-28,000736.html",
      "quote_link": "https://quote.eastmoney.com/unify/r/0.000736"
    },
    {
      "trade_date": "2025-04-28",
      "security_code": "000966",
      "security_name": "长源电力",
      "market_group": "SZ",
      "market_label": "深市",
      "change_rate": 5.8824,
      "trade_market_code": "069001002001",
      "security_type_code": "058001001",
      "detail_link": "https://data.eastmoney.com/stock/lhb,2025-04-28,000966.html",
      "quote_link": "https://quote.eastmoney.com/unify/r/0.000966"
    },
    {
      "trade_date": "2025-04-28",
      "security_code": "000993",
      "security_name": "闽东电力",
      "market_group": "SZ",
      "market_label": "深市",
      "change_rate": 9.8346,
      "trade_market_code": "069001002001",
      "security_type_code": "058001001",
      "detail_link": "https://data.eastmoney.com/stock/lhb,2025-04-28,000993.html",
      "quote_link": "https://quote.eastmoney.com/unify/r/0.000993"
    },
    {
      "trade_date": "2025-04-28",
      "security_code": "001331",
      "security_name": "胜通能源",
      "market_group": "SZ",
      "market_label": "深市",
      "change_rate": 4.2847,
      "trade_market_code": "069001002001",
      "security_type_code": "058001001",
      "detail_link": "https://data.eastmoney.com/stock/lhb,2025-04-28,001331.html",
      "quote_link": "https://quote.eastmoney.com/unify/r/0.001331"
    },
    {
      "trade_date": "2025-04-28",
      "security_code": "002094",
      "security_name": "青岛金王",
      "market_group": "SZ",
      "market_label": "深市",
      "change_rate": -9.466,
      "trade_market_code": "069001002001",
      "security_type_code": "058001001",
      "detail_link": "https://data.eastmoney.com/stock/lhb,2025-04-28,002094.html",
      "quote_link": "https://quote.eastmoney.com/unify/r/0.002094"
    },
    {
      "trade_date": "2025-04-28",
      "security_code": "002098",
      "security_name": "浔兴股份",
      "market_group": "SZ",
      "market_label": "深市",
      "change_rate": 9.9707,
      "trade_market_code": "069001002001",
      "security_type_code": "058001001",
      "detail_link": "https://data.eastmoney.com/stock/lhb,2025-04-28,002098.html",
      "quote_link": "https://quote.eastmoney.com/unify/r/0.002098"
    },
    {
      "trade_date": "2025-04-28",
      "security_code": "002165",
      "security_name": "红宝丽",
      "market_group": "SZ",
      "market_label": "深市",
      "change_rate": 4.0587,
      "trade_market_code": "069001002001",
      "security_type_code": "058001001",
      "detail_link": "https://data.eastmoney.com/stock/lhb,2025-04-28,002165.html",
      "quote_link": "https://quote.eastmoney.com/unify/r/0.002165"
    },
    {
      "trade_date": "2025-04-28",
      "security_code": "002194",
      "security_name": "武汉凡谷",
      "market_group": "SZ",
      "market_label": "深市",
      "change_rate": -9.9865,
      "trade_market_code": "069001002001",
      "security_type_code": "058001001",
      "detail_link": "https://data.eastmoney.com/stock/lhb,2025-04-28,002194.html",
      "quote_link": "https://quote.eastmoney.com/unify/r/0.002194"
    },
    {
      "trade_date": "2025-04-28",
      "security_code": "002197",
      "security_name": "证通电子",
      "market_group": "SZ",
      "market_label": "深市",
      "change_rate": 5.0439,
      "trade_market_code": "069001002001",
      "security_type_code": "058001001",
      "detail_link": "https://data.eastmoney.com/stock/lhb,2025-04-28,002197.html",
      "quote_link": "https://quote.eastmoney.com/unify/r/0.002197"
    },
    {
      "trade_date": "2025-04-28",
      "security_code": "002200",
      "security_name": "*ST交投",
      "market_group": "SZ",
      "market_label": "深市",
      "change_rate": 5.0445,
      "trade_market_code": "069001002005",
      "security_type_code": "058001001",
      "detail_link": "https://data.eastmoney.com/stock/lhb,2025-04-28,002200.html",
      "quote_link": "https://quote.eastmoney.com/unify/r/0.002200"
    },
    {
      "trade_date": "2025-04-28",
      "security_code": "002229",
      "security_name": "鸿博股份",
      "market_group": "SZ",
      "market_label": "深市",
      "change_rate": 9.9665,
      "trade_market_code": "069001002001",
      "security_type_code": "058001001",
      "detail_link": "https://data.eastmoney.com/stock/lhb,2025-04-28,002229.html",
      "quote_link": "https://quote.eastmoney.com/unify/r/0.002229"
    },
    {
      "trade_date": "2025-04-28",
      "security_code": "002289",
      "security_name": "*ST宇顺",
      "market_group": "SZ",
      "market_label": "深市",
      "change_rate": 5.0184,
      "trade_market_code": "069001002005",
      "security_type_code": "058001001",
      "detail_link": "https://data.eastmoney.com/stock/lhb,2025-04-28,002289.html",
      "quote_link": "https://quote.eastmoney.com/unify/r/0.002289"
    },
    {
      "trade_date": "2025-04-28",
      "security_code": "002298",
      "security_name": "中电鑫龙",
      "market_group": "SZ",
      "market_label": "深市",
      "change_rate": 10.0,
      "trade_market_code": "069001002001",
      "security_type_code": "058001001",
      "detail_link": "https://data.eastmoney.com/stock/lhb,2025-04-28,002298.html",
      "quote_link": "https://quote.eastmoney.com/unify/r/0.002298"
    },
    {
      "trade_date": "2025-04-28",
      "security_code": "002306",
      "security_name": "*ST云网",
      "market_group": "SZ",
      "market_label": "深市",
      "change_rate": -5.2326,
      "trade_market_code": "069001002005",
      "security_type_code": "058001001",
      "detail_link": "https://data.eastmoney.com/stock/lhb,2025-04-28,002306.html",
      "quote_link": "https://quote.eastmoney.com/unify/r/0.002306"
    },
    {
      "trade_date": "2025-04-28",
      "security_code": "002354",
      "security_name": "天娱数科",
      "market_group": "SZ",
      "market_label": "深市",
      "change_rate": 10.0671,
      "trade_market_code": "069001002001",
      "security_type_code": "058001001",
      "detail_link": "https://data.eastmoney.com/stock/lhb,2025-04-28,002354.html",
      "quote_link": "https://quote.eastmoney.com/unify/r/0.002354"
    },
    {
      "trade_date": "2025-04-28",
      "security_code": "002365",
      "security_name": "永安药业",
      "market_group": "SZ",
      "market_label": "深市",
      "change_rate": 10.0422,
      "trade_market_code": "069001002001",
      "security_type_code": "058001001",
      "detail_link": "https://data.eastmoney.com/stock/lhb,2025-04-28,002365.html",
      "quote_link": "https://quote.eastmoney.com/unify/r/0.002365"
    },
    {
      "trade_date": "2025-04-28",
      "security_code": "002537",
      "security_name": "海联金汇",
      "market_group": "SZ",
      "market_label": "深市",
      "change_rate": -10.0334,
      "trade_market_code": "069001002001",
      "security_type_code": "058001001",
      "detail_link": "https://data.eastmoney.com/stock/lhb,2025-04-28,002537.html",
      "quote_link": "https://quote.eastmoney.com/unify/r/0.002537"
    },
    {
      "trade_date": "2025-04-28",
      "security_code": "002564",
      "security_name": "天沃科技",
      "market_group": "SZ",
      "market_label": "深市",
      "change_rate": 10.0,
      "trade_market_code": "069001002001",
      "security_type_code": "058001001",
      "detail_link": "https://data.eastmoney.com/stock/lhb,2025-04-28,002564.html",
      "quote_link": "https://quote.eastmoney.com/unify/r/0.002564"
    },
    {
      "trade_date": "2025-04-28",
      "security_code": "002570",
      "security_name": "贝因美",
      "market_group": "SZ",
      "market_label": "深市",
      "change_rate": -9.9388,
      "trade_market_code": "069001002001",
      "security_type_code": "058001001",
      "detail_link": "https://data.eastmoney.com/stock/lhb,2025-04-28,002570.html",
      "quote_link": "https://quote.eastmoney.com/unify/r/0.002570"
    },
    {
      "trade_date": "2025-04-28",
      "security_code": "002809",
      "security_name": "红墙股份",
      "market_group": "SZ",
      "market_label": "深市",
      "change_rate": -3.1122,
      "trade_market_code": "069001002001",
      "security_type_code": "058001001",
      "detail_link": "https://data.eastmoney.com/stock/lhb,2025-04-28,002809.html",
      "quote_link": "https://quote.eastmoney.com/unify/r/0.002809"
    },
    {
      "trade_date": "2025-04-28",
      "security_code": "002908",
      "security_name": "德生科技",
      "market_group": "SZ",
      "market_label": "深市",
      "change_rate": 10.0228,
      "trade_market_code": "069001002001",
      "security_type_code": "058001001",
      "detail_link": "https://data.eastmoney.com/stock/lhb,2025-04-28,002908.html",
      "quote_link": "https://quote.eastmoney.com/unify/r/0.002908"
    },
    {
      "trade_date": "2025-04-28",
      "security_code": "002915",
      "security_name": "中欣氟材",
      "market_group": "SZ",
      "market_label": "深市",
      "change_rate": 5.2443,
      "trade_market_code": "069001002001",
      "security_type_code": "058001001",
      "detail_link": "https://data.eastmoney.com/stock/lhb,2025-04-28,002915.html",
      "quote_link": "https://quote.eastmoney.com/unify/r/0.002915"
    },
    {
      "trade_date": "2025-04-28",
      "security_code": "300040",
      "security_name": "九洲集团",
      "market_group": "SZ",
      "market_label": "深市",
      "change_rate": -4.0973,
      "trade_market_code": "069001002002",
      "security_type_code": "058001001",
      "detail_link": "https://data.eastmoney.com/stock/lhb,2025-04-28,300040.html",
      "quote_link": "https://quote.eastmoney.com/unify/r/0.300040"
    },
    {
      "trade_date": "2025-04-28",
      "security_code": "300044",
      "security_name": "ST赛为",
      "market_group": "SZ",
      "market_label": "深市",
      "change_rate": -19.9134,
      "trade_market_code": "069001002005",
      "security_type_code": "058001001",
      "detail_link": "https://data.eastmoney.com/stock/lhb,2025-04-28,300044.html",
      "quote_link": "https://quote.eastmoney.com/unify/r/0.300044"
    },
    {
      "trade_date": "2025-04-28",
      "security_code": "300157",
      "security_name": "新锦动力",
      "market_group": "SZ",
      "market_label": "深市",
      "change_rate": 19.9248,
      "trade_market_code": "069001002002",
      "security_type_code": "058001001",
      "detail_link": "https://data.eastmoney.com/stock/lhb,2025-04-28,300157.html",
      "quote_link": "https://quote.eastmoney.com/unify/r/0.300157"
    },
    {
      "trade_date": "2025-04-28",
      "security_code": "300205",
      "security_name": "*ST天喻",
      "market_group": "SZ",
      "market_label": "深市",
      "change_rate": -15.4839,
      "trade_market_code": "069001002005",
      "security_type_code": "058001001",
      "detail_link": "https://data.eastmoney.com/stock/lhb,2025-04-28,300205.html",
      "quote_link": "https://quote.eastmoney.com/unify/r/0.300205"
    },
    {
      "trade_date": "2025-04-28",
      "security_code": "300211",
      "security_name": "*ST亿通",
      "market_group": "SZ",
      "market_label": "深市",
      "change_rate": -19.977,
      "trade_market_code": "069001002005",
      "security_type_code": "058001001",
      "detail_link": "https://data.eastmoney.com/stock/lhb,2025-04-28,300211.html",
      "quote_link": "https://quote.eastmoney.com/unify/r/0.300211"
    },
    {
      "trade_date": "2025-04-28",
      "security_code": "300225",
      "security_name": "*ST金泰",
      "market_group": "SZ",
      "market_label": "深市",
      "change_rate": -11.7808,
      "trade_market_code": "069001002005",
      "security_type_code": "058001001",
      "detail_link": "https://data.eastmoney.com/stock/lhb,2025-04-28,300225.html",
      "quote_link": "https://quote.eastmoney.com/unify/r/0.300225"
    },
    {
      "trade_date": "2025-04-28",
      "security_code": "300379",
      "security_name": "东通退",
      "market_group": "SZ",
      "market_label": "深市",
      "change_rate": -20.0308,
      "trade_market_code": "069001002005",
      "security_type_code": "058001001",
      "detail_link": "https://data.eastmoney.com/stock/lhb,2025-04-28,300379.html",
      "quote_link": "https://quote.eastmoney.com/unify/r/0.300379"
    },
    {
      "trade_date": "2025-04-28",
      "security_code": "300477",
      "security_name": "ST合纵",
      "market_group": "SZ",
      "market_label": "深市",
      "change_rate": -20.0803,
      "trade_market_code": "069001002005",
      "security_type_code": "058001001",
      "detail_link": "https://data.eastmoney.com/stock/lhb,2025-04-28,300477.html",
      "quote_link": "https://quote.eastmoney.com/unify/r/0.300477"
    },
    {
      "trade_date": "2025-04-28",
      "security_code": "300561",
      "security_name": "*ST汇科",
      "market_group": "SZ",
      "market_label": "深市",
      "change_rate": -6.4298,
      "trade_market_code": "069001002005",
      "security_type_code": "058001001",
      "detail_link": "https://data.eastmoney.com/stock/lhb,2025-04-28,300561.html",
      "quote_link": "https://quote.eastmoney.com/unify/r/0.300561"
    },
    {
      "trade_date": "2025-04-28",
      "security_code": "300630",
      "security_name": "普利退",
      "market_group": "SZ",
      "market_label": "深市",
      "change_rate": -73.8956,
      "trade_market_code": "069001002005",
      "security_type_code": "058001001",
      "detail_link": "https://data.eastmoney.com/stock/lhb,2025-04-28,300630.html",
      "quote_link": "https://quote.eastmoney.com/unify/r/0.300630"
    },
    {
      "trade_date": "2025-04-28",
      "security_code": "300716",
      "security_name": "ST泉为",
      "market_group": "SZ",
      "market_label": "深市",
      "change_rate": -19.7406,
      "trade_market_code": "069001002005",
      "security_type_code": "058001001",
      "detail_link": "https://data.eastmoney.com/stock/lhb,2025-04-28,300716.html",
      "quote_link": "https://quote.eastmoney.com/unify/r/0.300716"
    },
    {
      "trade_date": "2025-04-28",
      "security_code": "300945",
      "security_name": "曼卡龙",
      "market_group": "SZ",
      "market_label": "深市",
      "change_rate": 15.102,
      "trade_market_code": "069001002002",
      "security_type_code": "058001001",
      "detail_link": "https://data.eastmoney.com/stock/lhb,2025-04-28,300945.html",
      "quote_link": "https://quote.eastmoney.com/unify/r/0.300945"
    },
    {
      "trade_date": "2025-04-28",
      "security_code": "301079",
      "security_name": "邵阳液压",
      "market_group": "SZ",
      "market_label": "深市",
      "change_rate": 4.4601,
      "trade_market_code": "069001002002",
      "security_type_code": "058001001",
      "detail_link": "https://data.eastmoney.com/stock/lhb,2025-04-28,301079.html",
      "quote_link": "https://quote.eastmoney.com/unify/r/0.301079"
    },
    {
      "trade_date": "2025-04-28",
      "security_code": "301209",
      "security_name": "联合化学",
      "market_group": "SZ",
      "market_label": "深市",
      "change_rate": 20.0,
      "trade_market_code": "069001002002",
      "security_type_code": "058001001",
      "detail_link": "https://data.eastmoney.com/stock/lhb,2025-04-28,301209.html",
      "quote_link": "https://quote.eastmoney.com/unify/r/0.301209"
    },
    {
      "trade_date": "2025-04-28",
      "security_code": "301212",
      "security_name": "联盛化学",
      "market_group": "SZ",
      "market_label": "深市",
      "change_rate": 19.9831,
      "trade_market_code": "069001002002",
      "security_type_code": "058001001",
      "detail_link": "https://data.eastmoney.com/stock/lhb,2025-04-28,301212.html",
      "quote_link": "https://quote.eastmoney.com/unify/r/0.301212"
    },
    {
      "trade_date": "2025-04-28",
      "security_code": "301225",
      "security_name": "恒勃股份",
      "market_group": "SZ",
      "market_label": "深市",
      "change_rate": 8.0295,
      "trade_market_code": "069001002002",
      "security_type_code": "058001001",
      "detail_link": "https://data.eastmoney.com/stock/lhb,2025-04-28,301225.html",
      "quote_link": "https://quote.eastmoney.com/unify/r/0.301225"
    },
    {
      "trade_date": "2025-04-28",
      "security_code": "301479",
      "security_name": "弘景光电",
      "market_group": "SZ",
      "market_label": "深市",
      "change_rate": 20.0,
      "trade_market_code": "069001002002",
      "security_type_code": "058001001",
      "detail_link": "https://data.eastmoney.com/stock/lhb,2025-04-28,301479.html",
      "quote_link": "https://quote.eastmoney.com/unify/r/0.301479"
    },
    {
      "trade_date": "2025-04-28",
      "security_code": "301535",
      "security_name": "浙江华远",
      "market_group": "SZ",
      "market_label": "深市",
      "change_rate": -11.9139,
      "trade_market_code": "069001002002",
      "security_type_code": "058001001",
      "detail_link": "https://data.eastmoney.com/stock/lhb,2025-04-28,301535.html",
      "quote_link": "https://quote.eastmoney.com/unify/r/0.301535"
    },
    {
      "trade_date": "2025-04-28",
      "security_code": "920046",
      "security_name": "亿能电力",
      "market_group": "BJ",
      "market_label": "京市",
      "change_rate": -4.8518,
      "trade_market_code": "069001017",
      "security_type_code": "058001001",
      "detail_link": "https://data.eastmoney.com/stock/lhb,2025-04-28,920046.html",
      "quote_link": "https://quote.eastmoney.com/unify/r/0.920046"
    },
    {
      "trade_date": "2025-04-28",
      "security_code": "920066",
      "security_name": "科拜尔",
      "market_group": "BJ",
      "market_label": "京市",
      "change_rate": -2.2222,
      "trade_market_code": "069001017",
      "security_type_code": "058001001",
      "detail_link": "https://data.eastmoney.com/stock/lhb,2025-04-28,920066.html",
      "quote_link": "https://quote.eastmoney.com/unify/r/0.920066"
    },
    {
      "trade_date": "2025-04-28",
      "security_code": "920123",
      "security_name": "芭薇股份",
      "market_group": "BJ",
      "market_label": "京市",
      "change_rate": -13.7511,
      "trade_market_code": "069001017",
      "security_type_code": "058001001",
      "detail_link": "https://data.eastmoney.com/stock/lhb,2025-04-28,920123.html",
      "quote_link": "https://quote.eastmoney.com/unify/r/0.920123"
    },
    {
      "trade_date": "2025-04-28",
      "security_code": "920299",
      "security_name": "灿能电力",
      "market_group": "BJ",
      "market_label": "京市",
      "change_rate": -2.693,
      "trade_market_code": "069001017",
      "security_type_code": "058001001",
      "detail_link": "https://data.eastmoney.com/stock/lhb,2025-04-28,920299.html",
      "quote_link": "https://quote.eastmoney.com/unify/r/0.920299"
    },
    {
      "trade_date": "2025-04-28",
      "security_code": "920305",
      "security_name": "*ST云创",
      "market_group": "BJ",
      "market_label": "京市",
      "change_rate": -29.9817,
      "trade_market_code": "069001017",
      "security_type_code": "058001001",
      "detail_link": "https://data.eastmoney.com/stock/lhb,2025-04-28,920305.html",
      "quote_link": "https://quote.eastmoney.com/unify/r/0.920305"
    },
    {
      "trade_date": "2025-04-28",
      "security_code": "920351",
      "security_name": "华光源海",
      "market_group": "BJ",
      "market_label": "京市",
      "change_rate": -3.6645,
      "trade_market_code": "069001017",
      "security_type_code": "058001001",
      "detail_link": "https://data.eastmoney.com/stock/lhb,2025-04-28,920351.html",
      "quote_link": "https://quote.eastmoney.com/unify/r/0.920351"
    },
    {
      "trade_date": "2025-04-28",
      "security_code": "123099",
      "security_name": "普利转退",
      "market_group": "KZZ",
      "market_label": "可转债",
      "change_rate": -18.1327,
      "trade_market_code": "069001002",
      "security_type_code": "060",
      "detail_link": "https://data.eastmoney.com/stock/lhb,2025-04-28,123099.html",
      "quote_link": "https://quote.eastmoney.com/unify/r/0.123099"
    }
  ]
}