{
  "date": "2025-11-05",
  "source_file": "lhb_overview_20250101_20260211.csv",
  "summary": {
    "total_count": 67,
    "up_count": 57,
    "down_count": 10,
    "flat_count": 0,
    "avg_change": 10.4956,
    "market_counts": {
      "HS": 24,
      "KCB": 5,
      "SZ": 32,
      "BJ": 5,
      "KZZ": 1
    }
  },
  "market_breakdown": [
    {
      "code": "BJ",
      "label": "京市",
      "count": 5
    },
    {
      "code": "HS",
      "label": "沪市",
      "count": 24
    },
    {
      "code": "KCB",
      "label": "科创板",
      "count": 5
    },
    {
      "code": "KZZ",
      "label": "可转债",
      "count": 1
    },
    {
      "code": "SZ",
      "label": "深市",
      "count": 32
    }
  ],
  "top_gainers": [
    {
      "trade_date": "2025-11-05",
      "security_code": "603334",
      "security_name": "丰倍生物",
      "market_group": "HS",
      "market_label": "沪市",
      "change_rate": 172.6011,
      "trade_market_code": "069001001001",
      "security_type_code": "058001001",
      "detail_link": "https://data.eastmoney.com/stock/lhb,2025-11-05,603334.html",
      "quote_link": "https://quote.eastmoney.com/unify/r/1.603334"
    },
    {
      "trade_date": "2025-11-05",
      "security_code": "920299",
      "security_name": "灿能电力",
      "market_group": "BJ",
      "market_label": "京市",
      "change_rate": 29.9582,
      "trade_market_code": "069001017",
      "security_type_code": "058001001",
      "detail_link": "https://data.eastmoney.com/stock/lhb,2025-11-05,920299.html",
      "quote_link": "https://quote.eastmoney.com/unify/r/0.920299"
    },
    {
      "trade_date": "2025-11-05",
      "security_code": "920046",
      "security_name": "亿能电力",
      "market_group": "BJ",
      "market_label": "京市",
      "change_rate": 20.7941,
      "trade_market_code": "069001017",
      "security_type_code": "058001001",
      "detail_link": "https://data.eastmoney.com/stock/lhb,2025-11-05,920046.html",
      "quote_link": "https://quote.eastmoney.com/unify/r/0.920046"
    },
    {
      "trade_date": "2025-11-05",
      "security_code": "300444",
      "security_name": "双杰电气",
      "market_group": "SZ",
      "market_label": "深市",
      "change_rate": 20.0243,
      "trade_market_code": "069001002002",
      "security_type_code": "058001001",
      "detail_link": "https://data.eastmoney.com/stock/lhb,2025-11-05,300444.html",
      "quote_link": "https://quote.eastmoney.com/unify/r/0.300444"
    },
    {
      "trade_date": "2025-11-05",
      "security_code": "688472",
      "security_name": "阿特斯",
      "market_group": "KCB",
      "market_label": "科创板",
      "change_rate": 20.0226,
      "trade_market_code": "069001001006",
      "security_type_code": "058001001",
      "detail_link": "https://data.eastmoney.com/stock/lhb,2025-11-05,688472.html",
      "quote_link": "https://quote.eastmoney.com/unify/r/1.688472"
    },
    {
      "trade_date": "2025-11-05",
      "security_code": "300669",
      "security_name": "沪宁股份",
      "market_group": "SZ",
      "market_label": "深市",
      "change_rate": 20.0,
      "trade_market_code": "069001002002",
      "security_type_code": "058001001",
      "detail_link": "https://data.eastmoney.com/stock/lhb,2025-11-05,300669.html",
      "quote_link": "https://quote.eastmoney.com/unify/r/0.300669"
    },
    {
      "trade_date": "2025-11-05",
      "security_code": "123234",
      "security_name": "中能转债",
      "market_group": "KZZ",
      "market_label": "可转债",
      "change_rate": 20.0,
      "trade_market_code": "069001002",
      "security_type_code": "060",
      "detail_link": "https://data.eastmoney.com/stock/lhb,2025-11-05,123234.html",
      "quote_link": "https://quote.eastmoney.com/unify/r/0.123234"
    },
    {
      "trade_date": "2025-11-05",
      "security_code": "301024",
      "security_name": "霍普股份",
      "market_group": "SZ",
      "market_label": "深市",
      "change_rate": 19.995,
      "trade_market_code": "069001002002",
      "security_type_code": "058001001",
      "detail_link": "https://data.eastmoney.com/stock/lhb,2025-11-05,301024.html",
      "quote_link": "https://quote.eastmoney.com/unify/r/0.301024"
    },
    {
      "trade_date": "2025-11-05",
      "security_code": "301361",
      "security_name": "众智科技",
      "market_group": "SZ",
      "market_label": "深市",
      "change_rate": 19.9882,
      "trade_market_code": "069001002002",
      "security_type_code": "058001001",
      "detail_link": "https://data.eastmoney.com/stock/lhb,2025-11-05,301361.html",
      "quote_link": "https://quote.eastmoney.com/unify/r/0.301361"
    },
    {
      "trade_date": "2025-11-05",
      "security_code": "688517",
      "security_name": "金冠电气",
      "market_group": "KCB",
      "market_label": "科创板",
      "change_rate": 19.9877,
      "trade_market_code": "069001001006",
      "security_type_code": "058001001",
      "detail_link": "https://data.eastmoney.com/stock/lhb,2025-11-05,688517.html",
      "quote_link": "https://quote.eastmoney.com/unify/r/1.688517"
    }
  ],
  "top_losers": [
    {
      "trade_date": "2025-11-05",
      "security_code": "688765",
      "security_name": "禾元生物",
      "market_group": "KCB",
      "market_label": "科创板",
      "change_rate": -12.5547,
      "trade_market_code": "069001001006",
      "security_type_code": "058001001",
      "detail_link": "https://data.eastmoney.com/stock/lhb,2025-11-05,688765.html",
      "quote_link": "https://quote.eastmoney.com/unify/r/1.688765"
    },
    {
      "trade_date": "2025-11-05",
      "security_code": "603823",
      "security_name": "百合花",
      "market_group": "HS",
      "market_label": "沪市",
      "change_rate": -10.0052,
      "trade_market_code": "069001001001",
      "security_type_code": "058001001",
      "detail_link": "https://data.eastmoney.com/stock/lhb,2025-11-05,603823.html",
      "quote_link": "https://quote.eastmoney.com/unify/r/1.603823"
    },
    {
      "trade_date": "2025-11-05",
      "security_code": "600593",
      "security_name": "大连圣亚",
      "market_group": "HS",
      "market_label": "沪市",
      "change_rate": -9.9936,
      "trade_market_code": "069001001001",
      "security_type_code": "058001001",
      "detail_link": "https://data.eastmoney.com/stock/lhb,2025-11-05,600593.html",
      "quote_link": "https://quote.eastmoney.com/unify/r/1.600593"
    },
    {
      "trade_date": "2025-11-05",
      "security_code": "603099",
      "security_name": "长白山",
      "market_group": "HS",
      "market_label": "沪市",
      "change_rate": -9.0658,
      "trade_market_code": "069001001001",
      "security_type_code": "058001001",
      "detail_link": "https://data.eastmoney.com/stock/lhb,2025-11-05,603099.html",
      "quote_link": "https://quote.eastmoney.com/unify/r/1.603099"
    },
    {
      "trade_date": "2025-11-05",
      "security_code": "003026",
      "security_name": "中晶科技",
      "market_group": "SZ",
      "market_label": "深市",
      "change_rate": -6.5564,
      "trade_market_code": "069001002001",
      "security_type_code": "058001001",
      "detail_link": "https://data.eastmoney.com/stock/lhb,2025-11-05,003026.html",
      "quote_link": "https://quote.eastmoney.com/unify/r/0.003026"
    },
    {
      "trade_date": "2025-11-05",
      "security_code": "603192",
      "security_name": "汇得科技",
      "market_group": "HS",
      "market_label": "沪市",
      "change_rate": -6.2545,
      "trade_market_code": "069001001001",
      "security_type_code": "058001001",
      "detail_link": "https://data.eastmoney.com/stock/lhb,2025-11-05,603192.html",
      "quote_link": "https://quote.eastmoney.com/unify/r/1.603192"
    },
    {
      "trade_date": "2025-11-05",
      "security_code": "603388",
      "security_name": "*ST元成",
      "market_group": "HS",
      "market_label": "沪市",
      "change_rate": -4.2857,
      "trade_market_code": "069001001003",
      "security_type_code": "058001001",
      "detail_link": "https://data.eastmoney.com/stock/lhb,2025-11-05,603388.html",
      "quote_link": "https://quote.eastmoney.com/unify/r/1.603388"
    },
    {
      "trade_date": "2025-11-05",
      "security_code": "603014",
      "security_name": "威高血净",
      "market_group": "HS",
      "market_label": "沪市",
      "change_rate": -3.9759,
      "trade_market_code": "069001001001",
      "security_type_code": "058001001",
      "detail_link": "https://data.eastmoney.com/stock/lhb,2025-11-05,603014.html",
      "quote_link": "https://quote.eastmoney.com/unify/r/1.603014"
    },
    {
      "trade_date": "2025-11-05",
      "security_code": "001386",
      "security_name": "马可波罗",
      "market_group": "SZ",
      "market_label": "深市",
      "change_rate": -0.4332,
      "trade_market_code": "069001002001",
      "security_type_code": "058001001",
      "detail_link": "https://data.eastmoney.com/stock/lhb,2025-11-05,001386.html",
      "quote_link": "https://quote.eastmoney.com/unify/r/0.001386"
    },
    {
      "trade_date": "2025-11-05",
      "security_code": "603175",
      "security_name": "超颖电子",
      "market_group": "HS",
      "market_label": "沪市",
      "change_rate": -0.0399,
      "trade_market_code": "069001001001",
      "security_type_code": "058001001",
      "detail_link": "https://data.eastmoney.com/stock/lhb,2025-11-05,603175.html",
      "quote_link": "https://quote.eastmoney.com/unify/r/1.603175"
    }
  ],
  "stocks": [
    {
      "trade_date": "2025-11-05",
      "security_code": "600089",
      "security_name": "特变电工",
      "market_group": "HS",
      "market_label": "沪市",
      "change_rate": 9.9909,
      "trade_market_code": "069001001001",
      "security_type_code": "058001001",
      "detail_link": "https://data.eastmoney.com/stock/lhb,2025-11-05,600089.html",
      "quote_link": "https://quote.eastmoney.com/unify/r/1.600089"
    },
    {
      "trade_date": "2025-11-05",
      "security_code": "600403",
      "security_name": "大有能源",
      "market_group": "HS",
      "market_label": "沪市",
      "change_rate": 5.9649,
      "trade_market_code": "069001001001",
      "security_type_code": "058001001",
      "detail_link": "https://data.eastmoney.com/stock/lhb,2025-11-05,600403.html",
      "quote_link": "https://quote.eastmoney.com/unify/r/1.600403"
    },
    {
      "trade_date": "2025-11-05",
      "security_code": "600408",
      "security_name": "安泰集团",
      "market_group": "HS",
      "market_label": "沪市",
      "change_rate": 10.1064,
      "trade_market_code": "069001001001",
      "security_type_code": "058001001",
      "detail_link": "https://data.eastmoney.com/stock/lhb,2025-11-05,600408.html",
      "quote_link": "https://quote.eastmoney.com/unify/r/1.600408"
    },
    {
      "trade_date": "2025-11-05",
      "security_code": "600506",
      "security_name": "统一股份",
      "market_group": "HS",
      "market_label": "沪市",
      "change_rate": 2.6472,
      "trade_market_code": "069001001001",
      "security_type_code": "058001001",
      "detail_link": "https://data.eastmoney.com/stock/lhb,2025-11-05,600506.html",
      "quote_link": "https://quote.eastmoney.com/unify/r/1.600506"
    },
    {
      "trade_date": "2025-11-05",
      "security_code": "600593",
      "security_name": "大连圣亚",
      "market_group": "HS",
      "market_label": "沪市",
      "change_rate": -9.9936,
      "trade_market_code": "069001001001",
      "security_type_code": "058001001",
      "detail_link": "https://data.eastmoney.com/stock/lhb,2025-11-05,600593.html",
      "quote_link": "https://quote.eastmoney.com/unify/r/1.600593"
    },
    {
      "trade_date": "2025-11-05",
      "security_code": "600608",
      "security_name": "*ST沪科",
      "market_group": "HS",
      "market_label": "沪市",
      "change_rate": 3.386,
      "trade_market_code": "069001001003",
      "security_type_code": "058001001",
      "detail_link": "https://data.eastmoney.com/stock/lhb,2025-11-05,600608.html",
      "quote_link": "https://quote.eastmoney.com/unify/r/1.600608"
    },
    {
      "trade_date": "2025-11-05",
      "security_code": "600759",
      "security_name": "洲际油气",
      "market_group": "HS",
      "market_label": "沪市",
      "change_rate": 10.1563,
      "trade_market_code": "069001001001",
      "security_type_code": "058001001",
      "detail_link": "https://data.eastmoney.com/stock/lhb,2025-11-05,600759.html",
      "quote_link": "https://quote.eastmoney.com/unify/r/1.600759"
    },
    {
      "trade_date": "2025-11-05",
      "security_code": "600815",
      "security_name": "厦工股份",
      "market_group": "HS",
      "market_label": "沪市",
      "change_rate": 10.089,
      "trade_market_code": "069001001001",
      "security_type_code": "058001001",
      "detail_link": "https://data.eastmoney.com/stock/lhb,2025-11-05,600815.html",
      "quote_link": "https://quote.eastmoney.com/unify/r/1.600815"
    },
    {
      "trade_date": "2025-11-05",
      "security_code": "601126",
      "security_name": "四方股份",
      "market_group": "HS",
      "market_label": "沪市",
      "change_rate": 8.1859,
      "trade_market_code": "069001001001",
      "security_type_code": "058001001",
      "detail_link": "https://data.eastmoney.com/stock/lhb,2025-11-05,601126.html",
      "quote_link": "https://quote.eastmoney.com/unify/r/1.601126"
    },
    {
      "trade_date": "2025-11-05",
      "security_code": "601929",
      "security_name": "吉视传媒",
      "market_group": "HS",
      "market_label": "沪市",
      "change_rate": 10.0446,
      "trade_market_code": "069001001001",
      "security_type_code": "058001001",
      "detail_link": "https://data.eastmoney.com/stock/lhb,2025-11-05,601929.html",
      "quote_link": "https://quote.eastmoney.com/unify/r/1.601929"
    },
    {
      "trade_date": "2025-11-05",
      "security_code": "603014",
      "security_name": "威高血净",
      "market_group": "HS",
      "market_label": "沪市",
      "change_rate": -3.9759,
      "trade_market_code": "069001001001",
      "security_type_code": "058001001",
      "detail_link": "https://data.eastmoney.com/stock/lhb,2025-11-05,603014.html",
      "quote_link": "https://quote.eastmoney.com/unify/r/1.603014"
    },
    {
      "trade_date": "2025-11-05",
      "security_code": "603067",
      "security_name": "振华股份",
      "market_group": "HS",
      "market_label": "沪市",
      "change_rate": 7.2345,
      "trade_market_code": "069001001001",
      "security_type_code": "058001001",
      "detail_link": "https://data.eastmoney.com/stock/lhb,2025-11-05,603067.html",
      "quote_link": "https://quote.eastmoney.com/unify/r/1.603067"
    },
    {
      "trade_date": "2025-11-05",
      "security_code": "603099",
      "security_name": "长白山",
      "market_group": "HS",
      "market_label": "沪市",
      "change_rate": -9.0658,
      "trade_market_code": "069001001001",
      "security_type_code": "058001001",
      "detail_link": "https://data.eastmoney.com/stock/lhb,2025-11-05,603099.html",
      "quote_link": "https://quote.eastmoney.com/unify/r/1.603099"
    },
    {
      "trade_date": "2025-11-05",
      "security_code": "603122",
      "security_name": "合富中国",
      "market_group": "HS",
      "market_label": "沪市",
      "change_rate": 10.0422,
      "trade_market_code": "069001001001",
      "security_type_code": "058001001",
      "detail_link": "https://data.eastmoney.com/stock/lhb,2025-11-05,603122.html",
      "quote_link": "https://quote.eastmoney.com/unify/r/1.603122"
    },
    {
      "trade_date": "2025-11-05",
      "security_code": "603175",
      "security_name": "超颖电子",
      "market_group": "HS",
      "market_label": "沪市",
      "change_rate": -0.0399,
      "trade_market_code": "069001001001",
      "security_type_code": "058001001",
      "detail_link": "https://data.eastmoney.com/stock/lhb,2025-11-05,603175.html",
      "quote_link": "https://quote.eastmoney.com/unify/r/1.603175"
    },
    {
      "trade_date": "2025-11-05",
      "security_code": "603192",
      "security_name": "汇得科技",
      "market_group": "HS",
      "market_label": "沪市",
      "change_rate": -6.2545,
      "trade_market_code": "069001001001",
      "security_type_code": "058001001",
      "detail_link": "https://data.eastmoney.com/stock/lhb,2025-11-05,603192.html",
      "quote_link": "https://quote.eastmoney.com/unify/r/1.603192"
    },
    {
      "trade_date": "2025-11-05",
      "security_code": "603312",
      "security_name": "西典新能",
      "market_group": "HS",
      "market_label": "沪市",
      "change_rate": 10.0094,
      "trade_market_code": "069001001001",
      "security_type_code": "058001001",
      "detail_link": "https://data.eastmoney.com/stock/lhb,2025-11-05,603312.html",
      "quote_link": "https://quote.eastmoney.com/unify/r/1.603312"
    },
    {
      "trade_date": "2025-11-05",
      "security_code": "603334",
      "security_name": "丰倍生物",
      "market_group": "HS",
      "market_label": "沪市",
      "change_rate": 172.6011,
      "trade_market_code": "069001001001",
      "security_type_code": "058001001",
      "detail_link": "https://data.eastmoney.com/stock/lhb,2025-11-05,603334.html",
      "quote_link": "https://quote.eastmoney.com/unify/r/1.603334"
    },
    {
      "trade_date": "2025-11-05",
      "security_code": "603388",
      "security_name": "*ST元成",
      "market_group": "HS",
      "market_label": "沪市",
      "change_rate": -4.2857,
      "trade_market_code": "069001001003",
      "security_type_code": "058001001",
      "detail_link": "https://data.eastmoney.com/stock/lhb,2025-11-05,603388.html",
      "quote_link": "https://quote.eastmoney.com/unify/r/1.603388"
    },
    {
      "trade_date": "2025-11-05",
      "security_code": "603530",
      "security_name": "神马电力",
      "market_group": "HS",
      "market_label": "沪市",
      "change_rate": 9.9955,
      "trade_market_code": "069001001001",
      "security_type_code": "058001001",
      "detail_link": "https://data.eastmoney.com/stock/lhb,2025-11-05,603530.html",
      "quote_link": "https://quote.eastmoney.com/unify/r/1.603530"
    },
    {
      "trade_date": "2025-11-05",
      "security_code": "603616",
      "security_name": "韩建河山",
      "market_group": "HS",
      "market_label": "沪市",
      "change_rate": 4.419,
      "trade_market_code": "069001001001",
      "security_type_code": "058001001",
      "detail_link": "https://data.eastmoney.com/stock/lhb,2025-11-05,603616.html",
      "quote_link": "https://quote.eastmoney.com/unify/r/1.603616"
    },
    {
      "trade_date": "2025-11-05",
      "security_code": "603686",
      "security_name": "福龙马",
      "market_group": "HS",
      "market_label": "沪市",
      "change_rate": 2.4798,
      "trade_market_code": "069001001001",
      "security_type_code": "058001001",
      "detail_link": "https://data.eastmoney.com/stock/lhb,2025-11-05,603686.html",
      "quote_link": "https://quote.eastmoney.com/unify/r/1.603686"
    },
    {
      "trade_date": "2025-11-05",
      "security_code": "603759",
      "security_name": "海天股份",
      "market_group": "HS",
      "market_label": "沪市",
      "change_rate": 9.9923,
      "trade_market_code": "069001001001",
      "security_type_code": "058001001",
      "detail_link": "https://data.eastmoney.com/stock/lhb,2025-11-05,603759.html",
      "quote_link": "https://quote.eastmoney.com/unify/r/1.603759"
    },
    {
      "trade_date": "2025-11-05",
      "security_code": "603823",
      "security_name": "百合花",
      "market_group": "HS",
      "market_label": "沪市",
      "change_rate": -10.0052,
      "trade_market_code": "069001001001",
      "security_type_code": "058001001",
      "detail_link": "https://data.eastmoney.com/stock/lhb,2025-11-05,603823.html",
      "quote_link": "https://quote.eastmoney.com/unify/r/1.603823"
    },
    {
      "trade_date": "2025-11-05",
      "security_code": "688472",
      "security_name": "阿特斯",
      "market_group": "KCB",
      "market_label": "科创板",
      "change_rate": 20.0226,
      "trade_market_code": "069001001006",
      "security_type_code": "058001001",
      "detail_link": "https://data.eastmoney.com/stock/lhb,2025-11-05,688472.html",
      "quote_link": "https://quote.eastmoney.com/unify/r/1.688472"
    },
    {
      "trade_date": "2025-11-05",
      "security_code": "688517",
      "security_name": "金冠电气",
      "market_group": "KCB",
      "market_label": "科创板",
      "change_rate": 19.9877,
      "trade_market_code": "069001001006",
      "security_type_code": "058001001",
      "detail_link": "https://data.eastmoney.com/stock/lhb,2025-11-05,688517.html",
      "quote_link": "https://quote.eastmoney.com/unify/r/1.688517"
    },
    {
      "trade_date": "2025-11-05",
      "security_code": "688676",
      "security_name": "金盘科技",
      "market_group": "KCB",
      "market_label": "科创板",
      "change_rate": 18.1191,
      "trade_market_code": "069001001006",
      "security_type_code": "058001001",
      "detail_link": "https://data.eastmoney.com/stock/lhb,2025-11-05,688676.html",
      "quote_link": "https://quote.eastmoney.com/unify/r/1.688676"
    },
    {
      "trade_date": "2025-11-05",
      "security_code": "688759",
      "security_name": "必贝特",
      "market_group": "KCB",
      "market_label": "科创板",
      "change_rate": 6.9466,
      "trade_market_code": "069001001006",
      "security_type_code": "058001001",
      "detail_link": "https://data.eastmoney.com/stock/lhb,2025-11-05,688759.html",
      "quote_link": "https://quote.eastmoney.com/unify/r/1.688759"
    },
    {
      "trade_date": "2025-11-05",
      "security_code": "688765",
      "security_name": "禾元生物",
      "market_group": "KCB",
      "market_label": "科创板",
      "change_rate": -12.5547,
      "trade_market_code": "069001001006",
      "security_type_code": "058001001",
      "detail_link": "https://data.eastmoney.com/stock/lhb,2025-11-05,688765.html",
      "quote_link": "https://quote.eastmoney.com/unify/r/1.688765"
    },
    {
      "trade_date": "2025-11-05",
      "security_code": "000572",
      "security_name": "海马汽车",
      "market_group": "SZ",
      "market_label": "深市",
      "change_rate": 10.0125,
      "trade_market_code": "069001002001",
      "security_type_code": "058001001",
      "detail_link": "https://data.eastmoney.com/stock/lhb,2025-11-05,000572.html",
      "quote_link": "https://quote.eastmoney.com/unify/r/0.000572"
    },
    {
      "trade_date": "2025-11-05",
      "security_code": "000592",
      "security_name": "平潭发展",
      "market_group": "SZ",
      "market_label": "深市",
      "change_rate": 10.035,
      "trade_market_code": "069001002001",
      "security_type_code": "058001001",
      "detail_link": "https://data.eastmoney.com/stock/lhb,2025-11-05,000592.html",
      "quote_link": "https://quote.eastmoney.com/unify/r/0.000592"
    },
    {
      "trade_date": "2025-11-05",
      "security_code": "000609",
      "security_name": "ST中迪",
      "market_group": "SZ",
      "market_label": "深市",
      "change_rate": 5.0063,
      "trade_market_code": "069001002005",
      "security_type_code": "058001001",
      "detail_link": "https://data.eastmoney.com/stock/lhb,2025-11-05,000609.html",
      "quote_link": "https://quote.eastmoney.com/unify/r/0.000609"
    },
    {
      "trade_date": "2025-11-05",
      "security_code": "000657",
      "security_name": "中钨高新",
      "market_group": "SZ",
      "market_label": "深市",
      "change_rate": 10.0132,
      "trade_market_code": "069001002001",
      "security_type_code": "058001001",
      "detail_link": "https://data.eastmoney.com/stock/lhb,2025-11-05,000657.html",
      "quote_link": "https://quote.eastmoney.com/unify/r/0.000657"
    },
    {
      "trade_date": "2025-11-05",
      "security_code": "000753",
      "security_name": "漳州发展",
      "market_group": "SZ",
      "market_label": "深市",
      "change_rate": 10.0,
      "trade_market_code": "069001002001",
      "security_type_code": "058001001",
      "detail_link": "https://data.eastmoney.com/stock/lhb,2025-11-05,000753.html",
      "quote_link": "https://quote.eastmoney.com/unify/r/0.000753"
    },
    {
      "trade_date": "2025-11-05",
      "security_code": "000993",
      "security_name": "闽东电力",
      "market_group": "SZ",
      "market_label": "深市",
      "change_rate": 10.0257,
      "trade_market_code": "069001002001",
      "security_type_code": "058001001",
      "detail_link": "https://data.eastmoney.com/stock/lhb,2025-11-05,000993.html",
      "quote_link": "https://quote.eastmoney.com/unify/r/0.000993"
    },
    {
      "trade_date": "2025-11-05",
      "security_code": "001255",
      "security_name": "博菲电气",
      "market_group": "SZ",
      "market_label": "深市",
      "change_rate": 10.0083,
      "trade_market_code": "069001002001",
      "security_type_code": "058001001",
      "detail_link": "https://data.eastmoney.com/stock/lhb,2025-11-05,001255.html",
      "quote_link": "https://quote.eastmoney.com/unify/r/0.001255"
    },
    {
      "trade_date": "2025-11-05",
      "security_code": "001386",
      "security_name": "马可波罗",
      "market_group": "SZ",
      "market_label": "深市",
      "change_rate": -0.4332,
      "trade_market_code": "069001002001",
      "security_type_code": "058001001",
      "detail_link": "https://data.eastmoney.com/stock/lhb,2025-11-05,001386.html",
      "quote_link": "https://quote.eastmoney.com/unify/r/0.001386"
    },
    {
      "trade_date": "2025-11-05",
      "security_code": "002076",
      "security_name": "*ST星光",
      "market_group": "SZ",
      "market_label": "深市",
      "change_rate": 4.9327,
      "trade_market_code": "069001002005",
      "security_type_code": "058001001",
      "detail_link": "https://data.eastmoney.com/stock/lhb,2025-11-05,002076.html",
      "quote_link": "https://quote.eastmoney.com/unify/r/0.002076"
    },
    {
      "trade_date": "2025-11-05",
      "security_code": "002112",
      "security_name": "三变科技",
      "market_group": "SZ",
      "market_label": "深市",
      "change_rate": 10.0344,
      "trade_market_code": "069001002001",
      "security_type_code": "058001001",
      "detail_link": "https://data.eastmoney.com/stock/lhb,2025-11-05,002112.html",
      "quote_link": "https://quote.eastmoney.com/unify/r/0.002112"
    },
    {
      "trade_date": "2025-11-05",
      "security_code": "002150",
      "security_name": "正泰电源",
      "market_group": "SZ",
      "market_label": "深市",
      "change_rate": 10.0048,
      "trade_market_code": "069001002001",
      "security_type_code": "058001001",
      "detail_link": "https://data.eastmoney.com/stock/lhb,2025-11-05,002150.html",
      "quote_link": "https://quote.eastmoney.com/unify/r/0.002150"
    },
    {
      "trade_date": "2025-11-05",
      "security_code": "002163",
      "security_name": "海南发展",
      "market_group": "SZ",
      "market_label": "深市",
      "change_rate": 9.9867,
      "trade_market_code": "069001002001",
      "security_type_code": "058001001",
      "detail_link": "https://data.eastmoney.com/stock/lhb,2025-11-05,002163.html",
      "quote_link": "https://quote.eastmoney.com/unify/r/0.002163"
    },
    {
      "trade_date": "2025-11-05",
      "security_code": "002181",
      "security_name": "粤传媒",
      "market_group": "SZ",
      "market_label": "深市",
      "change_rate": 3.1373,
      "trade_market_code": "069001002001",
      "security_type_code": "058001001",
      "detail_link": "https://data.eastmoney.com/stock/lhb,2025-11-05,002181.html",
      "quote_link": "https://quote.eastmoney.com/unify/r/0.002181"
    },
    {
      "trade_date": "2025-11-05",
      "security_code": "002213",
      "security_name": "大为股份",
      "market_group": "SZ",
      "market_label": "深市",
      "change_rate": 3.3197,
      "trade_market_code": "069001002001",
      "security_type_code": "058001001",
      "detail_link": "https://data.eastmoney.com/stock/lhb,2025-11-05,002213.html",
      "quote_link": "https://quote.eastmoney.com/unify/r/0.002213"
    },
    {
      "trade_date": "2025-11-05",
      "security_code": "002333",
      "security_name": "罗普斯金",
      "market_group": "SZ",
      "market_label": "深市",
      "change_rate": 10.0813,
      "trade_market_code": "069001002001",
      "security_type_code": "058001001",
      "detail_link": "https://data.eastmoney.com/stock/lhb,2025-11-05,002333.html",
      "quote_link": "https://quote.eastmoney.com/unify/r/0.002333"
    },
    {
      "trade_date": "2025-11-05",
      "security_code": "002418",
      "security_name": "康盛股份",
      "market_group": "SZ",
      "market_label": "深市",
      "change_rate": 6.9288,
      "trade_market_code": "069001002001",
      "security_type_code": "058001001",
      "detail_link": "https://data.eastmoney.com/stock/lhb,2025-11-05,002418.html",
      "quote_link": "https://quote.eastmoney.com/unify/r/0.002418"
    },
    {
      "trade_date": "2025-11-05",
      "security_code": "002451",
      "security_name": "摩恩电气",
      "market_group": "SZ",
      "market_label": "深市",
      "change_rate": 10.0128,
      "trade_market_code": "069001002001",
      "security_type_code": "058001001",
      "detail_link": "https://data.eastmoney.com/stock/lhb,2025-11-05,002451.html",
      "quote_link": "https://quote.eastmoney.com/unify/r/0.002451"
    },
    {
      "trade_date": "2025-11-05",
      "security_code": "002639",
      "security_name": "雪人集团",
      "market_group": "SZ",
      "market_label": "深市",
      "change_rate": 10.0402,
      "trade_market_code": "069001002001",
      "security_type_code": "058001001",
      "detail_link": "https://data.eastmoney.com/stock/lhb,2025-11-05,002639.html",
      "quote_link": "https://quote.eastmoney.com/unify/r/0.002639"
    },
    {
      "trade_date": "2025-11-05",
      "security_code": "002713",
      "security_name": "*ST东易",
      "market_group": "SZ",
      "market_label": "深市",
      "change_rate": 5.0199,
      "trade_market_code": "069001002005",
      "security_type_code": "058001001",
      "detail_link": "https://data.eastmoney.com/stock/lhb,2025-11-05,002713.html",
      "quote_link": "https://quote.eastmoney.com/unify/r/0.002713"
    },
    {
      "trade_date": "2025-11-05",
      "security_code": "002885",
      "security_name": "京泉华",
      "market_group": "SZ",
      "market_label": "深市",
      "change_rate": 9.9932,
      "trade_market_code": "069001002001",
      "security_type_code": "058001001",
      "detail_link": "https://data.eastmoney.com/stock/lhb,2025-11-05,002885.html",
      "quote_link": "https://quote.eastmoney.com/unify/r/0.002885"
    },
    {
      "trade_date": "2025-11-05",
      "security_code": "002922",
      "security_name": "伊戈尔",
      "market_group": "SZ",
      "market_label": "深市",
      "change_rate": 9.9926,
      "trade_market_code": "069001002001",
      "security_type_code": "058001001",
      "detail_link": "https://data.eastmoney.com/stock/lhb,2025-11-05,002922.html",
      "quote_link": "https://quote.eastmoney.com/unify/r/0.002922"
    },
    {
      "trade_date": "2025-11-05",
      "security_code": "003026",
      "security_name": "中晶科技",
      "market_group": "SZ",
      "market_label": "深市",
      "change_rate": -6.5564,
      "trade_market_code": "069001002001",
      "security_type_code": "058001001",
      "detail_link": "https://data.eastmoney.com/stock/lhb,2025-11-05,003026.html",
      "quote_link": "https://quote.eastmoney.com/unify/r/0.003026"
    },
    {
      "trade_date": "2025-11-05",
      "security_code": "300062",
      "security_name": "中能电气",
      "market_group": "SZ",
      "market_label": "深市",
      "change_rate": 19.9478,
      "trade_market_code": "069001002002",
      "security_type_code": "058001001",
      "detail_link": "https://data.eastmoney.com/stock/lhb,2025-11-05,300062.html",
      "quote_link": "https://quote.eastmoney.com/unify/r/0.300062"
    },
    {
      "trade_date": "2025-11-05",
      "security_code": "300259",
      "security_name": "新天科技",
      "market_group": "SZ",
      "market_label": "深市",
      "change_rate": 15.2174,
      "trade_market_code": "069001002002",
      "security_type_code": "058001001",
      "detail_link": "https://data.eastmoney.com/stock/lhb,2025-11-05,300259.html",
      "quote_link": "https://quote.eastmoney.com/unify/r/0.300259"
    },
    {
      "trade_date": "2025-11-05",
      "security_code": "300444",
      "security_name": "双杰电气",
      "market_group": "SZ",
      "market_label": "深市",
      "change_rate": 20.0243,
      "trade_market_code": "069001002002",
      "security_type_code": "058001001",
      "detail_link": "https://data.eastmoney.com/stock/lhb,2025-11-05,300444.html",
      "quote_link": "https://quote.eastmoney.com/unify/r/0.300444"
    },
    {
      "trade_date": "2025-11-05",
      "security_code": "300591",
      "security_name": "万里马",
      "market_group": "SZ",
      "market_label": "深市",
      "change_rate": 3.0869,
      "trade_market_code": "069001002002",
      "security_type_code": "058001001",
      "detail_link": "https://data.eastmoney.com/stock/lhb,2025-11-05,300591.html",
      "quote_link": "https://quote.eastmoney.com/unify/r/0.300591"
    },
    {
      "trade_date": "2025-11-05",
      "security_code": "300669",
      "security_name": "沪宁股份",
      "market_group": "SZ",
      "market_label": "深市",
      "change_rate": 20.0,
      "trade_market_code": "069001002002",
      "security_type_code": "058001001",
      "detail_link": "https://data.eastmoney.com/stock/lhb,2025-11-05,300669.html",
      "quote_link": "https://quote.eastmoney.com/unify/r/0.300669"
    },
    {
      "trade_date": "2025-11-05",
      "security_code": "300814",
      "security_name": "中富电路",
      "market_group": "SZ",
      "market_label": "深市",
      "change_rate": 13.218,
      "trade_market_code": "069001002002",
      "security_type_code": "058001001",
      "detail_link": "https://data.eastmoney.com/stock/lhb,2025-11-05,300814.html",
      "quote_link": "https://quote.eastmoney.com/unify/r/0.300814"
    },
    {
      "trade_date": "2025-11-05",
      "security_code": "301024",
      "security_name": "霍普股份",
      "market_group": "SZ",
      "market_label": "深市",
      "change_rate": 19.995,
      "trade_market_code": "069001002002",
      "security_type_code": "058001001",
      "detail_link": "https://data.eastmoney.com/stock/lhb,2025-11-05,301024.html",
      "quote_link": "https://quote.eastmoney.com/unify/r/0.301024"
    },
    {
      "trade_date": "2025-11-05",
      "security_code": "301120",
      "security_name": "新特电气",
      "market_group": "SZ",
      "market_label": "深市",
      "change_rate": 14.1013,
      "trade_market_code": "069001002002",
      "security_type_code": "058001001",
      "detail_link": "https://data.eastmoney.com/stock/lhb,2025-11-05,301120.html",
      "quote_link": "https://quote.eastmoney.com/unify/r/0.301120"
    },
    {
      "trade_date": "2025-11-05",
      "security_code": "301361",
      "security_name": "众智科技",
      "market_group": "SZ",
      "market_label": "深市",
      "change_rate": 19.9882,
      "trade_market_code": "069001002002",
      "security_type_code": "058001001",
      "detail_link": "https://data.eastmoney.com/stock/lhb,2025-11-05,301361.html",
      "quote_link": "https://quote.eastmoney.com/unify/r/0.301361"
    },
    {
      "trade_date": "2025-11-05",
      "security_code": "301668",
      "security_name": "昊创瑞通",
      "market_group": "SZ",
      "market_label": "深市",
      "change_rate": 6.6611,
      "trade_market_code": "069001002002",
      "security_type_code": "058001001",
      "detail_link": "https://data.eastmoney.com/stock/lhb,2025-11-05,301668.html",
      "quote_link": "https://quote.eastmoney.com/unify/r/0.301668"
    },
    {
      "trade_date": "2025-11-05",
      "security_code": "920009",
      "security_name": "丹娜生物",
      "market_group": "BJ",
      "market_label": "京市",
      "change_rate": 3.0706,
      "trade_market_code": "069001017",
      "security_type_code": "058001001",
      "detail_link": "https://data.eastmoney.com/stock/lhb,2025-11-05,920009.html",
      "quote_link": "https://quote.eastmoney.com/unify/r/0.920009"
    },
    {
      "trade_date": "2025-11-05",
      "security_code": "920046",
      "security_name": "亿能电力",
      "market_group": "BJ",
      "market_label": "京市",
      "change_rate": 20.7941,
      "trade_market_code": "069001017",
      "security_type_code": "058001001",
      "detail_link": "https://data.eastmoney.com/stock/lhb,2025-11-05,920046.html",
      "quote_link": "https://quote.eastmoney.com/unify/r/0.920046"
    },
    {
      "trade_date": "2025-11-05",
      "security_code": "920062",
      "security_name": "科润智控",
      "market_group": "BJ",
      "market_label": "京市",
      "change_rate": 5.6315,
      "trade_market_code": "069001017",
      "security_type_code": "058001001",
      "detail_link": "https://data.eastmoney.com/stock/lhb,2025-11-05,920062.html",
      "quote_link": "https://quote.eastmoney.com/unify/r/0.920062"
    },
    {
      "trade_date": "2025-11-05",
      "security_code": "920299",
      "security_name": "灿能电力",
      "market_group": "BJ",
      "market_label": "京市",
      "change_rate": 29.9582,
      "trade_market_code": "069001017",
      "security_type_code": "058001001",
      "detail_link": "https://data.eastmoney.com/stock/lhb,2025-11-05,920299.html",
      "quote_link": "https://quote.eastmoney.com/unify/r/0.920299"
    },
    {
      "trade_date": "2025-11-05",
      "security_code": "920826",
      "security_name": "盖世食品",
      "market_group": "BJ",
      "market_label": "京市",
      "change_rate": 3.6711,
      "trade_market_code": "069001017",
      "security_type_code": "058001001",
      "detail_link": "https://data.eastmoney.com/stock/lhb,2025-11-05,920826.html",
      "quote_link": "https://quote.eastmoney.com/unify/r/0.920826"
    },
    {
      "trade_date": "2025-11-05",
      "security_code": "123234",
      "security_name": "中能转债",
      "market_group": "KZZ",
      "market_label": "可转债",
      "change_rate": 20.0,
      "trade_market_code": "069001002",
      "security_type_code": "060",
      "detail_link": "https://data.eastmoney.com/stock/lhb,2025-11-05,123234.html",
      "quote_link": "https://quote.eastmoney.com/unify/r/0.123234"
    }
  ]
}