{
  "date": "2026-01-16",
  "source_file": "lhb_overview_20260101_20260211.csv",
  "summary": {
    "total_count": 75,
    "up_count": 42,
    "down_count": 33,
    "flat_count": 0,
    "avg_change": 3.3974,
    "market_counts": {
      "HS": 23,
      "KCB": 7,
      "SZ": 36,
      "BJ": 6,
      "KZZ": 3
    }
  },
  "market_breakdown": [
    {
      "code": "BJ",
      "label": "京市",
      "count": 6
    },
    {
      "code": "HS",
      "label": "沪市",
      "count": 23
    },
    {
      "code": "KCB",
      "label": "科创板",
      "count": 7
    },
    {
      "code": "KZZ",
      "label": "可转债",
      "count": 3
    },
    {
      "code": "SZ",
      "label": "深市",
      "count": 36
    }
  ],
  "top_gainers": [
    {
      "trade_date": "2026-01-16",
      "security_code": "111024",
      "security_name": "澳弘转债",
      "market_group": "KZZ",
      "market_label": "可转债",
      "change_rate": 57.3,
      "trade_market_code": "069001001",
      "security_type_code": "060",
      "detail_link": "https://data.eastmoney.com/stock/lhb,2026-01-16,111024.html",
      "quote_link": "https://quote.eastmoney.com/unify/r/1.111024"
    },
    {
      "trade_date": "2026-01-16",
      "security_code": "123264",
      "security_name": "双乐转债",
      "market_group": "KZZ",
      "market_label": "可转债",
      "change_rate": 57.3,
      "trade_market_code": "069001002",
      "security_type_code": "060",
      "detail_link": "https://data.eastmoney.com/stock/lhb,2026-01-16,123264.html",
      "quote_link": "https://quote.eastmoney.com/unify/r/0.123264"
    },
    {
      "trade_date": "2026-01-16",
      "security_code": "920179",
      "security_name": "凯德石英",
      "market_group": "BJ",
      "market_label": "京市",
      "change_rate": 20.2755,
      "trade_market_code": "069001017",
      "security_type_code": "058001001",
      "detail_link": "https://data.eastmoney.com/stock/lhb,2026-01-16,920179.html",
      "quote_link": "https://quote.eastmoney.com/unify/r/0.920179"
    },
    {
      "trade_date": "2026-01-16",
      "security_code": "301235",
      "security_name": "华康洁净",
      "market_group": "SZ",
      "market_label": "深市",
      "change_rate": 20.01,
      "trade_market_code": "069001002002",
      "security_type_code": "058001001",
      "detail_link": "https://data.eastmoney.com/stock/lhb,2026-01-16,301235.html",
      "quote_link": "https://quote.eastmoney.com/unify/r/0.301235"
    },
    {
      "trade_date": "2026-01-16",
      "security_code": "688376",
      "security_name": "美埃科技",
      "market_group": "KCB",
      "market_label": "科创板",
      "change_rate": 20.0,
      "trade_market_code": "069001001006",
      "security_type_code": "058001001",
      "detail_link": "https://data.eastmoney.com/stock/lhb,2026-01-16,688376.html",
      "quote_link": "https://quote.eastmoney.com/unify/r/1.688376"
    },
    {
      "trade_date": "2026-01-16",
      "security_code": "300215",
      "security_name": "电科院",
      "market_group": "SZ",
      "market_label": "深市",
      "change_rate": 20.0,
      "trade_market_code": "069001002002",
      "security_type_code": "058001001",
      "detail_link": "https://data.eastmoney.com/stock/lhb,2026-01-16,300215.html",
      "quote_link": "https://quote.eastmoney.com/unify/r/0.300215"
    },
    {
      "trade_date": "2026-01-16",
      "security_code": "300606",
      "security_name": "金太阳",
      "market_group": "SZ",
      "market_label": "深市",
      "change_rate": 20.0,
      "trade_market_code": "069001002002",
      "security_type_code": "058001001",
      "detail_link": "https://data.eastmoney.com/stock/lhb,2026-01-16,300606.html",
      "quote_link": "https://quote.eastmoney.com/unify/r/0.300606"
    },
    {
      "trade_date": "2026-01-16",
      "security_code": "301529",
      "security_name": "福赛科技",
      "market_group": "SZ",
      "market_label": "深市",
      "change_rate": 19.9984,
      "trade_market_code": "069001002002",
      "security_type_code": "058001001",
      "detail_link": "https://data.eastmoney.com/stock/lhb,2026-01-16,301529.html",
      "quote_link": "https://quote.eastmoney.com/unify/r/0.301529"
    },
    {
      "trade_date": "2026-01-16",
      "security_code": "688234",
      "security_name": "天岳先进",
      "market_group": "KCB",
      "market_label": "科创板",
      "change_rate": 19.9978,
      "trade_market_code": "069001001006",
      "security_type_code": "058001001",
      "detail_link": "https://data.eastmoney.com/stock/lhb,2026-01-16,688234.html",
      "quote_link": "https://quote.eastmoney.com/unify/r/1.688234"
    },
    {
      "trade_date": "2026-01-16",
      "security_code": "688362",
      "security_name": "甬矽电子",
      "market_group": "KCB",
      "market_label": "科创板",
      "change_rate": 19.9954,
      "trade_market_code": "069001001006",
      "security_type_code": "058001001",
      "detail_link": "https://data.eastmoney.com/stock/lhb,2026-01-16,688362.html",
      "quote_link": "https://quote.eastmoney.com/unify/r/1.688362"
    }
  ],
  "top_losers": [
    {
      "trade_date": "2026-01-16",
      "security_code": "300391",
      "security_name": "*ST长药",
      "market_group": "SZ",
      "market_label": "深市",
      "change_rate": -20.5882,
      "trade_market_code": "069001002005",
      "security_type_code": "058001001",
      "detail_link": "https://data.eastmoney.com/stock/lhb,2026-01-16,300391.html",
      "quote_link": "https://quote.eastmoney.com/unify/r/0.300391"
    },
    {
      "trade_date": "2026-01-16",
      "security_code": "300986",
      "security_name": "志特新材",
      "market_group": "SZ",
      "market_label": "深市",
      "change_rate": -20.012,
      "trade_market_code": "069001002002",
      "security_type_code": "058001001",
      "detail_link": "https://data.eastmoney.com/stock/lhb,2026-01-16,300986.html",
      "quote_link": "https://quote.eastmoney.com/unify/r/0.300986"
    },
    {
      "trade_date": "2026-01-16",
      "security_code": "300344",
      "security_name": "*ST立方",
      "market_group": "SZ",
      "market_label": "深市",
      "change_rate": -19.2771,
      "trade_market_code": "069001002005",
      "security_type_code": "058001001",
      "detail_link": "https://data.eastmoney.com/stock/lhb,2026-01-16,300344.html",
      "quote_link": "https://quote.eastmoney.com/unify/r/0.300344"
    },
    {
      "trade_date": "2026-01-16",
      "security_code": "300111",
      "security_name": "向日葵",
      "market_group": "SZ",
      "market_label": "深市",
      "change_rate": -17.9435,
      "trade_market_code": "069001002002",
      "security_type_code": "058001001",
      "detail_link": "https://data.eastmoney.com/stock/lhb,2026-01-16,300111.html",
      "quote_link": "https://quote.eastmoney.com/unify/r/0.300111"
    },
    {
      "trade_date": "2026-01-16",
      "security_code": "688319",
      "security_name": "欧林生物",
      "market_group": "KCB",
      "market_label": "科创板",
      "change_rate": -15.2107,
      "trade_market_code": "069001001006",
      "security_type_code": "058001001",
      "detail_link": "https://data.eastmoney.com/stock/lhb,2026-01-16,688319.html",
      "quote_link": "https://quote.eastmoney.com/unify/r/1.688319"
    },
    {
      "trade_date": "2026-01-16",
      "security_code": "300758",
      "security_name": "七彩化学",
      "market_group": "SZ",
      "market_label": "深市",
      "change_rate": -15.0841,
      "trade_market_code": "069001002002",
      "security_type_code": "058001001",
      "detail_link": "https://data.eastmoney.com/stock/lhb,2026-01-16,300758.html",
      "quote_link": "https://quote.eastmoney.com/unify/r/0.300758"
    },
    {
      "trade_date": "2026-01-16",
      "security_code": "920021",
      "security_name": "流金科技",
      "market_group": "BJ",
      "market_label": "京市",
      "change_rate": -13.9453,
      "trade_market_code": "069001017",
      "security_type_code": "058001001",
      "detail_link": "https://data.eastmoney.com/stock/lhb,2026-01-16,920021.html",
      "quote_link": "https://quote.eastmoney.com/unify/r/0.920021"
    },
    {
      "trade_date": "2026-01-16",
      "security_code": "600340",
      "security_name": "华夏幸福",
      "market_group": "HS",
      "market_label": "沪市",
      "change_rate": -10.2273,
      "trade_market_code": "069001001001",
      "security_type_code": "058001001",
      "detail_link": "https://data.eastmoney.com/stock/lhb,2026-01-16,600340.html",
      "quote_link": "https://quote.eastmoney.com/unify/r/1.600340"
    },
    {
      "trade_date": "2026-01-16",
      "security_code": "600662",
      "security_name": "外服控股",
      "market_group": "HS",
      "market_label": "沪市",
      "change_rate": -10.0291,
      "trade_market_code": "069001001001",
      "security_type_code": "058001001",
      "detail_link": "https://data.eastmoney.com/stock/lhb,2026-01-16,600662.html",
      "quote_link": "https://quote.eastmoney.com/unify/r/1.600662"
    },
    {
      "trade_date": "2026-01-16",
      "security_code": "002446",
      "security_name": "盛路通信",
      "market_group": "SZ",
      "market_label": "深市",
      "change_rate": -10.0204,
      "trade_market_code": "069001002001",
      "security_type_code": "058001001",
      "detail_link": "https://data.eastmoney.com/stock/lhb,2026-01-16,002446.html",
      "quote_link": "https://quote.eastmoney.com/unify/r/0.002446"
    }
  ],
  "stocks": [
    {
      "trade_date": "2026-01-16",
      "security_code": "600058",
      "security_name": "五矿发展",
      "market_group": "HS",
      "market_label": "沪市",
      "change_rate": 10.0237,
      "trade_market_code": "069001001001",
      "security_type_code": "058001001",
      "detail_link": "https://data.eastmoney.com/stock/lhb,2026-01-16,600058.html",
      "quote_link": "https://quote.eastmoney.com/unify/r/1.600058"
    },
    {
      "trade_date": "2026-01-16",
      "security_code": "600151",
      "security_name": "航天机电",
      "market_group": "HS",
      "market_label": "沪市",
      "change_rate": -8.6389,
      "trade_market_code": "069001001001",
      "security_type_code": "058001001",
      "detail_link": "https://data.eastmoney.com/stock/lhb,2026-01-16,600151.html",
      "quote_link": "https://quote.eastmoney.com/unify/r/1.600151"
    },
    {
      "trade_date": "2026-01-16",
      "security_code": "600198",
      "security_name": "大唐电信",
      "market_group": "HS",
      "market_label": "沪市",
      "change_rate": 9.9728,
      "trade_market_code": "069001001001",
      "security_type_code": "058001001",
      "detail_link": "https://data.eastmoney.com/stock/lhb,2026-01-16,600198.html",
      "quote_link": "https://quote.eastmoney.com/unify/r/1.600198"
    },
    {
      "trade_date": "2026-01-16",
      "security_code": "600340",
      "security_name": "华夏幸福",
      "market_group": "HS",
      "market_label": "沪市",
      "change_rate": -10.2273,
      "trade_market_code": "069001001001",
      "security_type_code": "058001001",
      "detail_link": "https://data.eastmoney.com/stock/lhb,2026-01-16,600340.html",
      "quote_link": "https://quote.eastmoney.com/unify/r/1.600340"
    },
    {
      "trade_date": "2026-01-16",
      "security_code": "600410",
      "security_name": "华胜天成",
      "market_group": "HS",
      "market_label": "沪市",
      "change_rate": -9.9509,
      "trade_market_code": "069001001001",
      "security_type_code": "058001001",
      "detail_link": "https://data.eastmoney.com/stock/lhb,2026-01-16,600410.html",
      "quote_link": "https://quote.eastmoney.com/unify/r/1.600410"
    },
    {
      "trade_date": "2026-01-16",
      "security_code": "600537",
      "security_name": "亿晶光电",
      "market_group": "HS",
      "market_label": "沪市",
      "change_rate": -10.0,
      "trade_market_code": "069001001001",
      "security_type_code": "058001001",
      "detail_link": "https://data.eastmoney.com/stock/lhb,2026-01-16,600537.html",
      "quote_link": "https://quote.eastmoney.com/unify/r/1.600537"
    },
    {
      "trade_date": "2026-01-16",
      "security_code": "600589",
      "security_name": "大位科技",
      "market_group": "HS",
      "market_label": "沪市",
      "change_rate": -6.1463,
      "trade_market_code": "069001001001",
      "security_type_code": "058001001",
      "detail_link": "https://data.eastmoney.com/stock/lhb,2026-01-16,600589.html",
      "quote_link": "https://quote.eastmoney.com/unify/r/1.600589"
    },
    {
      "trade_date": "2026-01-16",
      "security_code": "600637",
      "security_name": "东方明珠",
      "market_group": "HS",
      "market_label": "沪市",
      "change_rate": -10.0,
      "trade_market_code": "069001001001",
      "security_type_code": "058001001",
      "detail_link": "https://data.eastmoney.com/stock/lhb,2026-01-16,600637.html",
      "quote_link": "https://quote.eastmoney.com/unify/r/1.600637"
    },
    {
      "trade_date": "2026-01-16",
      "security_code": "600662",
      "security_name": "外服控股",
      "market_group": "HS",
      "market_label": "沪市",
      "change_rate": -10.0291,
      "trade_market_code": "069001001001",
      "security_type_code": "058001001",
      "detail_link": "https://data.eastmoney.com/stock/lhb,2026-01-16,600662.html",
      "quote_link": "https://quote.eastmoney.com/unify/r/1.600662"
    },
    {
      "trade_date": "2026-01-16",
      "security_code": "600703",
      "security_name": "三安光电",
      "market_group": "HS",
      "market_label": "沪市",
      "change_rate": 10.0348,
      "trade_market_code": "069001001001",
      "security_type_code": "058001001",
      "detail_link": "https://data.eastmoney.com/stock/lhb,2026-01-16,600703.html",
      "quote_link": "https://quote.eastmoney.com/unify/r/1.600703"
    },
    {
      "trade_date": "2026-01-16",
      "security_code": "600776",
      "security_name": "东方通信",
      "market_group": "HS",
      "market_label": "沪市",
      "change_rate": -10.0043,
      "trade_market_code": "069001001001",
      "security_type_code": "058001001",
      "detail_link": "https://data.eastmoney.com/stock/lhb,2026-01-16,600776.html",
      "quote_link": "https://quote.eastmoney.com/unify/r/1.600776"
    },
    {
      "trade_date": "2026-01-16",
      "security_code": "600783",
      "security_name": "鲁信创投",
      "market_group": "HS",
      "market_label": "沪市",
      "change_rate": -9.9844,
      "trade_market_code": "069001001001",
      "security_type_code": "058001001",
      "detail_link": "https://data.eastmoney.com/stock/lhb,2026-01-16,600783.html",
      "quote_link": "https://quote.eastmoney.com/unify/r/1.600783"
    },
    {
      "trade_date": "2026-01-16",
      "security_code": "600841",
      "security_name": "动力新科",
      "market_group": "HS",
      "market_label": "沪市",
      "change_rate": 10.0324,
      "trade_market_code": "069001001001",
      "security_type_code": "058001001",
      "detail_link": "https://data.eastmoney.com/stock/lhb,2026-01-16,600841.html",
      "quote_link": "https://quote.eastmoney.com/unify/r/1.600841"
    },
    {
      "trade_date": "2026-01-16",
      "security_code": "601133",
      "security_name": "柏诚股份",
      "market_group": "HS",
      "market_label": "沪市",
      "change_rate": 10.0233,
      "trade_market_code": "069001001001",
      "security_type_code": "058001001",
      "detail_link": "https://data.eastmoney.com/stock/lhb,2026-01-16,601133.html",
      "quote_link": "https://quote.eastmoney.com/unify/r/1.601133"
    },
    {
      "trade_date": "2026-01-16",
      "security_code": "601616",
      "security_name": "广电电气",
      "market_group": "HS",
      "market_label": "沪市",
      "change_rate": 10.0962,
      "trade_market_code": "069001001001",
      "security_type_code": "058001001",
      "detail_link": "https://data.eastmoney.com/stock/lhb,2026-01-16,601616.html",
      "quote_link": "https://quote.eastmoney.com/unify/r/1.601616"
    },
    {
      "trade_date": "2026-01-16",
      "security_code": "603163",
      "security_name": "圣晖集成",
      "market_group": "HS",
      "market_label": "沪市",
      "change_rate": 10.0048,
      "trade_market_code": "069001001001",
      "security_type_code": "058001001",
      "detail_link": "https://data.eastmoney.com/stock/lhb,2026-01-16,603163.html",
      "quote_link": "https://quote.eastmoney.com/unify/r/1.603163"
    },
    {
      "trade_date": "2026-01-16",
      "security_code": "603179",
      "security_name": "新泉股份",
      "market_group": "HS",
      "market_label": "沪市",
      "change_rate": 10.0,
      "trade_market_code": "069001001001",
      "security_type_code": "058001001",
      "detail_link": "https://data.eastmoney.com/stock/lhb,2026-01-16,603179.html",
      "quote_link": "https://quote.eastmoney.com/unify/r/1.603179"
    },
    {
      "trade_date": "2026-01-16",
      "security_code": "603280",
      "security_name": "南方路机",
      "market_group": "HS",
      "market_label": "沪市",
      "change_rate": 4.439,
      "trade_market_code": "069001001001",
      "security_type_code": "058001001",
      "detail_link": "https://data.eastmoney.com/stock/lhb,2026-01-16,603280.html",
      "quote_link": "https://quote.eastmoney.com/unify/r/1.603280"
    },
    {
      "trade_date": "2026-01-16",
      "security_code": "603402",
      "security_name": "陕西旅游",
      "market_group": "HS",
      "market_label": "沪市",
      "change_rate": -0.3465,
      "trade_market_code": "069001001001",
      "security_type_code": "058001001",
      "detail_link": "https://data.eastmoney.com/stock/lhb,2026-01-16,603402.html",
      "quote_link": "https://quote.eastmoney.com/unify/r/1.603402"
    },
    {
      "trade_date": "2026-01-16",
      "security_code": "603665",
      "security_name": "康隆达",
      "market_group": "HS",
      "market_label": "沪市",
      "change_rate": 10.0153,
      "trade_market_code": "069001001001",
      "security_type_code": "058001001",
      "detail_link": "https://data.eastmoney.com/stock/lhb,2026-01-16,603665.html",
      "quote_link": "https://quote.eastmoney.com/unify/r/1.603665"
    },
    {
      "trade_date": "2026-01-16",
      "security_code": "603888",
      "security_name": "新华网",
      "market_group": "HS",
      "market_label": "沪市",
      "change_rate": -10.0103,
      "trade_market_code": "069001001001",
      "security_type_code": "058001001",
      "detail_link": "https://data.eastmoney.com/stock/lhb,2026-01-16,603888.html",
      "quote_link": "https://quote.eastmoney.com/unify/r/1.603888"
    },
    {
      "trade_date": "2026-01-16",
      "security_code": "605287",
      "security_name": "德才股份",
      "market_group": "HS",
      "market_label": "沪市",
      "change_rate": 6.1795,
      "trade_market_code": "069001001001",
      "security_type_code": "058001001",
      "detail_link": "https://data.eastmoney.com/stock/lhb,2026-01-16,605287.html",
      "quote_link": "https://quote.eastmoney.com/unify/r/1.605287"
    },
    {
      "trade_date": "2026-01-16",
      "security_code": "900920",
      "security_name": "动力B股",
      "market_group": "HS",
      "market_label": "沪市",
      "change_rate": 10.0,
      "trade_market_code": "069001001001",
      "security_type_code": "058001002",
      "detail_link": "https://data.eastmoney.com/stock/lhb,2026-01-16,900920.html",
      "quote_link": "https://quote.eastmoney.com/unify/r/1.900920"
    },
    {
      "trade_date": "2026-01-16",
      "security_code": "688234",
      "security_name": "天岳先进",
      "market_group": "KCB",
      "market_label": "科创板",
      "change_rate": 19.9978,
      "trade_market_code": "069001001006",
      "security_type_code": "058001001",
      "detail_link": "https://data.eastmoney.com/stock/lhb,2026-01-16,688234.html",
      "quote_link": "https://quote.eastmoney.com/unify/r/1.688234"
    },
    {
      "trade_date": "2026-01-16",
      "security_code": "688319",
      "security_name": "欧林生物",
      "market_group": "KCB",
      "market_label": "科创板",
      "change_rate": -15.2107,
      "trade_market_code": "069001001006",
      "security_type_code": "058001001",
      "detail_link": "https://data.eastmoney.com/stock/lhb,2026-01-16,688319.html",
      "quote_link": "https://quote.eastmoney.com/unify/r/1.688319"
    },
    {
      "trade_date": "2026-01-16",
      "security_code": "688334",
      "security_name": "西高院",
      "market_group": "KCB",
      "market_label": "科创板",
      "change_rate": 19.5041,
      "trade_market_code": "069001001006",
      "security_type_code": "058001001",
      "detail_link": "https://data.eastmoney.com/stock/lhb,2026-01-16,688334.html",
      "quote_link": "https://quote.eastmoney.com/unify/r/1.688334"
    },
    {
      "trade_date": "2026-01-16",
      "security_code": "688362",
      "security_name": "甬矽电子",
      "market_group": "KCB",
      "market_label": "科创板",
      "change_rate": 19.9954,
      "trade_market_code": "069001001006",
      "security_type_code": "058001001",
      "detail_link": "https://data.eastmoney.com/stock/lhb,2026-01-16,688362.html",
      "quote_link": "https://quote.eastmoney.com/unify/r/1.688362"
    },
    {
      "trade_date": "2026-01-16",
      "security_code": "688376",
      "security_name": "美埃科技",
      "market_group": "KCB",
      "market_label": "科创板",
      "change_rate": 20.0,
      "trade_market_code": "069001001006",
      "security_type_code": "058001001",
      "detail_link": "https://data.eastmoney.com/stock/lhb,2026-01-16,688376.html",
      "quote_link": "https://quote.eastmoney.com/unify/r/1.688376"
    },
    {
      "trade_date": "2026-01-16",
      "security_code": "688525",
      "security_name": "佰维存储",
      "market_group": "KCB",
      "market_label": "科创板",
      "change_rate": 17.19,
      "trade_market_code": "069001001006",
      "security_type_code": "058001001",
      "detail_link": "https://data.eastmoney.com/stock/lhb,2026-01-16,688525.html",
      "quote_link": "https://quote.eastmoney.com/unify/r/1.688525"
    },
    {
      "trade_date": "2026-01-16",
      "security_code": "688727",
      "security_name": "恒坤新材",
      "market_group": "KCB",
      "market_label": "科创板",
      "change_rate": 4.3594,
      "trade_market_code": "069001001006",
      "security_type_code": "058001001",
      "detail_link": "https://data.eastmoney.com/stock/lhb,2026-01-16,688727.html",
      "quote_link": "https://quote.eastmoney.com/unify/r/1.688727"
    },
    {
      "trade_date": "2026-01-16",
      "security_code": "000620",
      "security_name": "盈新发展",
      "market_group": "SZ",
      "market_label": "深市",
      "change_rate": 10.1639,
      "trade_market_code": "069001002001",
      "security_type_code": "058001001",
      "detail_link": "https://data.eastmoney.com/stock/lhb,2026-01-16,000620.html",
      "quote_link": "https://quote.eastmoney.com/unify/r/0.000620"
    },
    {
      "trade_date": "2026-01-16",
      "security_code": "001208",
      "security_name": "华菱线缆",
      "market_group": "SZ",
      "market_label": "深市",
      "change_rate": 7.1158,
      "trade_market_code": "069001002001",
      "security_type_code": "058001001",
      "detail_link": "https://data.eastmoney.com/stock/lhb,2026-01-16,001208.html",
      "quote_link": "https://quote.eastmoney.com/unify/r/0.001208"
    },
    {
      "trade_date": "2026-01-16",
      "security_code": "001331",
      "security_name": "胜通能源",
      "market_group": "SZ",
      "market_label": "深市",
      "change_rate": -5.0162,
      "trade_market_code": "069001002001",
      "security_type_code": "058001001",
      "detail_link": "https://data.eastmoney.com/stock/lhb,2026-01-16,001331.html",
      "quote_link": "https://quote.eastmoney.com/unify/r/0.001331"
    },
    {
      "trade_date": "2026-01-16",
      "security_code": "002028",
      "security_name": "思源电气",
      "market_group": "SZ",
      "market_label": "深市",
      "change_rate": 10.0,
      "trade_market_code": "069001002001",
      "security_type_code": "058001001",
      "detail_link": "https://data.eastmoney.com/stock/lhb,2026-01-16,002028.html",
      "quote_link": "https://quote.eastmoney.com/unify/r/0.002028"
    },
    {
      "trade_date": "2026-01-16",
      "security_code": "002044",
      "security_name": "美年健康",
      "market_group": "SZ",
      "market_label": "深市",
      "change_rate": -9.9882,
      "trade_market_code": "069001002001",
      "security_type_code": "058001001",
      "detail_link": "https://data.eastmoney.com/stock/lhb,2026-01-16,002044.html",
      "quote_link": "https://quote.eastmoney.com/unify/r/0.002044"
    },
    {
      "trade_date": "2026-01-16",
      "security_code": "002048",
      "security_name": "宁波华翔",
      "market_group": "SZ",
      "market_label": "深市",
      "change_rate": 10.0068,
      "trade_market_code": "069001002001",
      "security_type_code": "058001001",
      "detail_link": "https://data.eastmoney.com/stock/lhb,2026-01-16,002048.html",
      "quote_link": "https://quote.eastmoney.com/unify/r/0.002048"
    },
    {
      "trade_date": "2026-01-16",
      "security_code": "002112",
      "security_name": "三变科技",
      "market_group": "SZ",
      "market_label": "深市",
      "change_rate": -5.5792,
      "trade_market_code": "069001002001",
      "security_type_code": "058001001",
      "detail_link": "https://data.eastmoney.com/stock/lhb,2026-01-16,002112.html",
      "quote_link": "https://quote.eastmoney.com/unify/r/0.002112"
    },
    {
      "trade_date": "2026-01-16",
      "security_code": "002114",
      "security_name": "罗平锌电",
      "market_group": "SZ",
      "market_label": "深市",
      "change_rate": -4.1379,
      "trade_market_code": "069001002001",
      "security_type_code": "058001001",
      "detail_link": "https://data.eastmoney.com/stock/lhb,2026-01-16,002114.html",
      "quote_link": "https://quote.eastmoney.com/unify/r/0.002114"
    },
    {
      "trade_date": "2026-01-16",
      "security_code": "002119",
      "security_name": "康强电子",
      "market_group": "SZ",
      "market_label": "深市",
      "change_rate": 10.0201,
      "trade_market_code": "069001002001",
      "security_type_code": "058001001",
      "detail_link": "https://data.eastmoney.com/stock/lhb,2026-01-16,002119.html",
      "quote_link": "https://quote.eastmoney.com/unify/r/0.002119"
    },
    {
      "trade_date": "2026-01-16",
      "security_code": "002156",
      "security_name": "通富微电",
      "market_group": "SZ",
      "market_label": "深市",
      "change_rate": 10.0,
      "trade_market_code": "069001002001",
      "security_type_code": "058001001",
      "detail_link": "https://data.eastmoney.com/stock/lhb,2026-01-16,002156.html",
      "quote_link": "https://quote.eastmoney.com/unify/r/0.002156"
    },
    {
      "trade_date": "2026-01-16",
      "security_code": "002202",
      "security_name": "金风科技",
      "market_group": "SZ",
      "market_label": "深市",
      "change_rate": -9.9867,
      "trade_market_code": "069001002001",
      "security_type_code": "058001001",
      "detail_link": "https://data.eastmoney.com/stock/lhb,2026-01-16,002202.html",
      "quote_link": "https://quote.eastmoney.com/unify/r/0.002202"
    },
    {
      "trade_date": "2026-01-16",
      "security_code": "002218",
      "security_name": "拓日新能",
      "market_group": "SZ",
      "market_label": "深市",
      "change_rate": -8.0357,
      "trade_market_code": "069001002001",
      "security_type_code": "058001001",
      "detail_link": "https://data.eastmoney.com/stock/lhb,2026-01-16,002218.html",
      "quote_link": "https://quote.eastmoney.com/unify/r/0.002218"
    },
    {
      "trade_date": "2026-01-16",
      "security_code": "002400",
      "security_name": "省广集团",
      "market_group": "SZ",
      "market_label": "深市",
      "change_rate": -10.0,
      "trade_market_code": "069001002001",
      "security_type_code": "058001001",
      "detail_link": "https://data.eastmoney.com/stock/lhb,2026-01-16,002400.html",
      "quote_link": "https://quote.eastmoney.com/unify/r/0.002400"
    },
    {
      "trade_date": "2026-01-16",
      "security_code": "002446",
      "security_name": "盛路通信",
      "market_group": "SZ",
      "market_label": "深市",
      "change_rate": -10.0204,
      "trade_market_code": "069001002001",
      "security_type_code": "058001001",
      "detail_link": "https://data.eastmoney.com/stock/lhb,2026-01-16,002446.html",
      "quote_link": "https://quote.eastmoney.com/unify/r/0.002446"
    },
    {
      "trade_date": "2026-01-16",
      "security_code": "002554",
      "security_name": "惠博普",
      "market_group": "SZ",
      "market_label": "深市",
      "change_rate": -3.3248,
      "trade_market_code": "069001002001",
      "security_type_code": "058001001",
      "detail_link": "https://data.eastmoney.com/stock/lhb,2026-01-16,002554.html",
      "quote_link": "https://quote.eastmoney.com/unify/r/0.002554"
    },
    {
      "trade_date": "2026-01-16",
      "security_code": "002639",
      "security_name": "雪人集团",
      "market_group": "SZ",
      "market_label": "深市",
      "change_rate": -9.9876,
      "trade_market_code": "069001002001",
      "security_type_code": "058001001",
      "detail_link": "https://data.eastmoney.com/stock/lhb,2026-01-16,002639.html",
      "quote_link": "https://quote.eastmoney.com/unify/r/0.002639"
    },
    {
      "trade_date": "2026-01-16",
      "security_code": "002788",
      "security_name": "鹭燕医药",
      "market_group": "SZ",
      "market_label": "深市",
      "change_rate": -10.0137,
      "trade_market_code": "069001002001",
      "security_type_code": "058001001",
      "detail_link": "https://data.eastmoney.com/stock/lhb,2026-01-16,002788.html",
      "quote_link": "https://quote.eastmoney.com/unify/r/0.002788"
    },
    {
      "trade_date": "2026-01-16",
      "security_code": "002792",
      "security_name": "通宇通讯",
      "market_group": "SZ",
      "market_label": "深市",
      "change_rate": -8.7524,
      "trade_market_code": "069001002001",
      "security_type_code": "058001001",
      "detail_link": "https://data.eastmoney.com/stock/lhb,2026-01-16,002792.html",
      "quote_link": "https://quote.eastmoney.com/unify/r/0.002792"
    },
    {
      "trade_date": "2026-01-16",
      "security_code": "002796",
      "security_name": "世嘉科技",
      "market_group": "SZ",
      "market_label": "深市",
      "change_rate": 10.0,
      "trade_market_code": "069001002001",
      "security_type_code": "058001001",
      "detail_link": "https://data.eastmoney.com/stock/lhb,2026-01-16,002796.html",
      "quote_link": "https://quote.eastmoney.com/unify/r/0.002796"
    },
    {
      "trade_date": "2026-01-16",
      "security_code": "002842",
      "security_name": "翔鹭钨业",
      "market_group": "SZ",
      "market_label": "深市",
      "change_rate": 0.8359,
      "trade_market_code": "069001002001",
      "security_type_code": "058001001",
      "detail_link": "https://data.eastmoney.com/stock/lhb,2026-01-16,002842.html",
      "quote_link": "https://quote.eastmoney.com/unify/r/0.002842"
    },
    {
      "trade_date": "2026-01-16",
      "security_code": "300111",
      "security_name": "向日葵",
      "market_group": "SZ",
      "market_label": "深市",
      "change_rate": -17.9435,
      "trade_market_code": "069001002002",
      "security_type_code": "058001001",
      "detail_link": "https://data.eastmoney.com/stock/lhb,2026-01-16,300111.html",
      "quote_link": "https://quote.eastmoney.com/unify/r/0.300111"
    },
    {
      "trade_date": "2026-01-16",
      "security_code": "300215",
      "security_name": "电科院",
      "market_group": "SZ",
      "market_label": "深市",
      "change_rate": 20.0,
      "trade_market_code": "069001002002",
      "security_type_code": "058001001",
      "detail_link": "https://data.eastmoney.com/stock/lhb,2026-01-16,300215.html",
      "quote_link": "https://quote.eastmoney.com/unify/r/0.300215"
    },
    {
      "trade_date": "2026-01-16",
      "security_code": "300344",
      "security_name": "*ST立方",
      "market_group": "SZ",
      "market_label": "深市",
      "change_rate": -19.2771,
      "trade_market_code": "069001002005",
      "security_type_code": "058001001",
      "detail_link": "https://data.eastmoney.com/stock/lhb,2026-01-16,300344.html",
      "quote_link": "https://quote.eastmoney.com/unify/r/0.300344"
    },
    {
      "trade_date": "2026-01-16",
      "security_code": "300379",
      "security_name": "东通退",
      "market_group": "SZ",
      "market_label": "深市",
      "change_rate": -9.5238,
      "trade_market_code": "069001002005",
      "security_type_code": "058001001",
      "detail_link": "https://data.eastmoney.com/stock/lhb,2026-01-16,300379.html",
      "quote_link": "https://quote.eastmoney.com/unify/r/0.300379"
    },
    {
      "trade_date": "2026-01-16",
      "security_code": "300391",
      "security_name": "*ST长药",
      "market_group": "SZ",
      "market_label": "深市",
      "change_rate": -20.5882,
      "trade_market_code": "069001002005",
      "security_type_code": "058001001",
      "detail_link": "https://data.eastmoney.com/stock/lhb,2026-01-16,300391.html",
      "quote_link": "https://quote.eastmoney.com/unify/r/0.300391"
    },
    {
      "trade_date": "2026-01-16",
      "security_code": "300427",
      "security_name": "红相股份",
      "market_group": "SZ",
      "market_label": "深市",
      "change_rate": 11.3329,
      "trade_market_code": "069001002002",
      "security_type_code": "058001001",
      "detail_link": "https://data.eastmoney.com/stock/lhb,2026-01-16,300427.html",
      "quote_link": "https://quote.eastmoney.com/unify/r/0.300427"
    },
    {
      "trade_date": "2026-01-16",
      "security_code": "300606",
      "security_name": "金太阳",
      "market_group": "SZ",
      "market_label": "深市",
      "change_rate": 20.0,
      "trade_market_code": "069001002002",
      "security_type_code": "058001001",
      "detail_link": "https://data.eastmoney.com/stock/lhb,2026-01-16,300606.html",
      "quote_link": "https://quote.eastmoney.com/unify/r/0.300606"
    },
    {
      "trade_date": "2026-01-16",
      "security_code": "300758",
      "security_name": "七彩化学",
      "market_group": "SZ",
      "market_label": "深市",
      "change_rate": -15.0841,
      "trade_market_code": "069001002002",
      "security_type_code": "058001001",
      "detail_link": "https://data.eastmoney.com/stock/lhb,2026-01-16,300758.html",
      "quote_link": "https://quote.eastmoney.com/unify/r/0.300758"
    },
    {
      "trade_date": "2026-01-16",
      "security_code": "300780",
      "security_name": "德恩精工",
      "market_group": "SZ",
      "market_label": "深市",
      "change_rate": 19.9796,
      "trade_market_code": "069001002002",
      "security_type_code": "058001001",
      "detail_link": "https://data.eastmoney.com/stock/lhb,2026-01-16,300780.html",
      "quote_link": "https://quote.eastmoney.com/unify/r/0.300780"
    },
    {
      "trade_date": "2026-01-16",
      "security_code": "300986",
      "security_name": "志特新材",
      "market_group": "SZ",
      "market_label": "深市",
      "change_rate": -20.012,
      "trade_market_code": "069001002002",
      "security_type_code": "058001001",
      "detail_link": "https://data.eastmoney.com/stock/lhb,2026-01-16,300986.html",
      "quote_link": "https://quote.eastmoney.com/unify/r/0.300986"
    },
    {
      "trade_date": "2026-01-16",
      "security_code": "301235",
      "security_name": "华康洁净",
      "market_group": "SZ",
      "market_label": "深市",
      "change_rate": 20.01,
      "trade_market_code": "069001002002",
      "security_type_code": "058001001",
      "detail_link": "https://data.eastmoney.com/stock/lhb,2026-01-16,301235.html",
      "quote_link": "https://quote.eastmoney.com/unify/r/0.301235"
    },
    {
      "trade_date": "2026-01-16",
      "security_code": "301348",
      "security_name": "蓝箭电子",
      "market_group": "SZ",
      "market_label": "深市",
      "change_rate": 13.5073,
      "trade_market_code": "069001002002",
      "security_type_code": "058001001",
      "detail_link": "https://data.eastmoney.com/stock/lhb,2026-01-16,301348.html",
      "quote_link": "https://quote.eastmoney.com/unify/r/0.301348"
    },
    {
      "trade_date": "2026-01-16",
      "security_code": "301529",
      "security_name": "福赛科技",
      "market_group": "SZ",
      "market_label": "深市",
      "change_rate": 19.9984,
      "trade_market_code": "069001002002",
      "security_type_code": "058001001",
      "detail_link": "https://data.eastmoney.com/stock/lhb,2026-01-16,301529.html",
      "quote_link": "https://quote.eastmoney.com/unify/r/0.301529"
    },
    {
      "trade_date": "2026-01-16",
      "security_code": "301563",
      "security_name": "云汉芯城",
      "market_group": "SZ",
      "market_label": "深市",
      "change_rate": 5.182,
      "trade_market_code": "069001002002",
      "security_type_code": "058001001",
      "detail_link": "https://data.eastmoney.com/stock/lhb,2026-01-16,301563.html",
      "quote_link": "https://quote.eastmoney.com/unify/r/0.301563"
    },
    {
      "trade_date": "2026-01-16",
      "security_code": "301595",
      "security_name": "太力科技",
      "market_group": "SZ",
      "market_label": "深市",
      "change_rate": 10.5263,
      "trade_market_code": "069001002002",
      "security_type_code": "058001001",
      "detail_link": "https://data.eastmoney.com/stock/lhb,2026-01-16,301595.html",
      "quote_link": "https://quote.eastmoney.com/unify/r/0.301595"
    },
    {
      "trade_date": "2026-01-16",
      "security_code": "301629",
      "security_name": "矽电股份",
      "market_group": "SZ",
      "market_label": "深市",
      "change_rate": 3.39,
      "trade_market_code": "069001002002",
      "security_type_code": "058001001",
      "detail_link": "https://data.eastmoney.com/stock/lhb,2026-01-16,301629.html",
      "quote_link": "https://quote.eastmoney.com/unify/r/0.301629"
    },
    {
      "trade_date": "2026-01-16",
      "security_code": "920021",
      "security_name": "流金科技",
      "market_group": "BJ",
      "market_label": "京市",
      "change_rate": -13.9453,
      "trade_market_code": "069001017",
      "security_type_code": "058001001",
      "detail_link": "https://data.eastmoney.com/stock/lhb,2026-01-16,920021.html",
      "quote_link": "https://quote.eastmoney.com/unify/r/0.920021"
    },
    {
      "trade_date": "2026-01-16",
      "security_code": "920046",
      "security_name": "亿能电力",
      "market_group": "BJ",
      "market_label": "京市",
      "change_rate": 0.1593,
      "trade_market_code": "069001017",
      "security_type_code": "058001001",
      "detail_link": "https://data.eastmoney.com/stock/lhb,2026-01-16,920046.html",
      "quote_link": "https://quote.eastmoney.com/unify/r/0.920046"
    },
    {
      "trade_date": "2026-01-16",
      "security_code": "920179",
      "security_name": "凯德石英",
      "market_group": "BJ",
      "market_label": "京市",
      "change_rate": 20.2755,
      "trade_market_code": "069001017",
      "security_type_code": "058001001",
      "detail_link": "https://data.eastmoney.com/stock/lhb,2026-01-16,920179.html",
      "quote_link": "https://quote.eastmoney.com/unify/r/0.920179"
    },
    {
      "trade_date": "2026-01-16",
      "security_code": "920227",
      "security_name": "美登科技",
      "market_group": "BJ",
      "market_label": "京市",
      "change_rate": -9.1573,
      "trade_market_code": "069001017",
      "security_type_code": "058001001",
      "detail_link": "https://data.eastmoney.com/stock/lhb,2026-01-16,920227.html",
      "quote_link": "https://quote.eastmoney.com/unify/r/0.920227"
    },
    {
      "trade_date": "2026-01-16",
      "security_code": "920299",
      "security_name": "灿能电力",
      "market_group": "BJ",
      "market_label": "京市",
      "change_rate": -0.2924,
      "trade_market_code": "069001017",
      "security_type_code": "058001001",
      "detail_link": "https://data.eastmoney.com/stock/lhb,2026-01-16,920299.html",
      "quote_link": "https://quote.eastmoney.com/unify/r/0.920299"
    },
    {
      "trade_date": "2026-01-16",
      "security_code": "920706",
      "security_name": "铁拓机械",
      "market_group": "BJ",
      "market_label": "京市",
      "change_rate": 10.1624,
      "trade_market_code": "069001017",
      "security_type_code": "058001001",
      "detail_link": "https://data.eastmoney.com/stock/lhb,2026-01-16,920706.html",
      "quote_link": "https://quote.eastmoney.com/unify/r/0.920706"
    },
    {
      "trade_date": "2026-01-16",
      "security_code": "111024",
      "security_name": "澳弘转债",
      "market_group": "KZZ",
      "market_label": "可转债",
      "change_rate": 57.3,
      "trade_market_code": "069001001",
      "security_type_code": "060",
      "detail_link": "https://data.eastmoney.com/stock/lhb,2026-01-16,111024.html",
      "quote_link": "https://quote.eastmoney.com/unify/r/1.111024"
    },
    {
      "trade_date": "2026-01-16",
      "security_code": "123251",
      "security_name": "华医转债",
      "market_group": "KZZ",
      "market_label": "可转债",
      "change_rate": 16.8889,
      "trade_market_code": "069001002",
      "security_type_code": "060",
      "detail_link": "https://data.eastmoney.com/stock/lhb,2026-01-16,123251.html",
      "quote_link": "https://quote.eastmoney.com/unify/r/0.123251"
    },
    {
      "trade_date": "2026-01-16",
      "security_code": "123264",
      "security_name": "双乐转债",
      "market_group": "KZZ",
      "market_label": "可转债",
      "change_rate": 57.3,
      "trade_market_code": "069001002",
      "security_type_code": "060",
      "detail_link": "https://data.eastmoney.com/stock/lhb,2026-01-16,123264.html",
      "quote_link": "https://quote.eastmoney.com/unify/r/0.123264"
    }
  ]
}